[{"name":"Precious Achiuwa","ppg":"8.3","apg":"1.0","rpg":"5.3","position":"C","age":"23","fgPct":".418","teamId":"TOR","stlPerG":"0.4","blkPerG":"0.7"},{"name":"Steven Adams","ppg":"8.4","apg":"2.3","rpg":"11.3","position":"C","age":"29","fgPct":".599","teamId":"MEM","stlPerG":"0.8","blkPerG":"1.1"},{"name":"Bam Adebayo","ppg":"21.5","apg":"3.0","rpg":"10.1","position":"C","age":"25","fgPct":".540","teamId":"MIA","stlPerG":"1.1","blkPerG":"0.9"},{"name":"Ochai Agbaji","ppg":"4.1","apg":"0.4","rpg":"1.5","position":"SG","age":"22","fgPct":".494","teamId":"UTA","stlPerG":"0.1","blkPerG":"0.2"},{"name":"Santi Aldama","ppg":"9.6","apg":"1.2","rpg":"4.9","position":"PF","age":"22","fgPct":".490","teamId":"MEM","stlPerG":"0.7","blkPerG":"0.8"},{"name":"Nickeil Alexander-Walker","ppg":"6.8","apg":"2.2","rpg":"1.8","position":"SG","age":"24","fgPct":".491","teamId":"UTA","stlPerG":"0.7","blkPerG":"0.4"},{"name":"Grayson Allen","ppg":"10.8","apg":"2.6","rpg":"3.6","position":"SG","age":"27","fgPct":".444","teamId":"MIL","stlPerG":"0.8","blkPerG":"0.2"},{"name":"Jarrett Allen","ppg":"13.9","apg":"1.7","rpg":"9.8","position":"C","age":"24","fgPct":".631","teamId":"CLE","stlPerG":"0.8","blkPerG":"1.2"},{"name":"Jose Alvarado","ppg":"9.2","apg":"3.1","rpg":"2.5","position":"PG","age":"24","fgPct":".411","teamId":"NOP","stlPerG":"1.2","blkPerG":"0.2"},{"name":"Kyle Anderson","ppg":"8.4","apg":"4.1","rpg":"4.8","position":"PF","age":"29","fgPct":".511","teamId":"MIN","stlPerG":"1.3","blkPerG":"0.8"},{"name":"Giannis Antetokounmpo","ppg":"31.0","apg":"5.3","rpg":"11.9","position":"PF","age":"28","fgPct":".524","teamId":"MIL","stlPerG":"0.8","blkPerG":"0.9"},{"name":"Thanasis Antetokounmpo","ppg":"0.5","apg":"0.2","rpg":"1.0","position":"SF","age":"30","fgPct":".214","teamId":"MIL","stlPerG":"0.1","blkPerG":"0.2"},{"name":"Cole Anthony","ppg":"11.4","apg":"4.3","rpg":"4.5","position":"PG","age":"22","fgPct":".406","teamId":"ORL","stlPerG":"0.7","blkPerG":"0.4"},{"name":"OG Anunoby","ppg":"17.5","apg":"2.1","rpg":"5.8","position":"SF","age":"25","fgPct":".456","teamId":"TOR","stlPerG":"2.1","blkPerG":"0.8"},{"name":"Ryan Arcidiacono","ppg":"0.3","apg":"0.2","rpg":"0.4","position":"PG","age":"28","fgPct":".200","teamId":"NYK","stlPerG":"0.2","blkPerG":"0.0"},{"name":"Deni Avdija","ppg":"8.2","apg":"2.6","rpg":"6.0","position":"SF","age":"22","fgPct":".429","teamId":"WAS","stlPerG":"0.7","blkPerG":"0.6"},{"name":"Deandre Ayton","ppg":"17.5","apg":"2.1","rpg":"9.9","position":"C","age":"24","fgPct":".583","teamId":"PHO","stlPerG":"0.5","blkPerG":"0.7"},{"name":"Udoka Azubuike","ppg":"1.6","apg":"0.3","rpg":"1.7","position":"C","age":"23","fgPct":".857","teamId":"UTA","stlPerG":"0.1","blkPerG":"0.2"},{"name":"Marvin Bagley III","ppg":"10.6","apg":"0.6","rpg":"5.9","position":"C","age":"23","fgPct":".537","teamId":"DET","stlPerG":"0.5","blkPerG":"0.7"},{"name":"Patrick Baldwin Jr.","ppg":"5.2","apg":"0.2","rpg":"1.5","position":"SF","age":"20","fgPct":".431","teamId":"GSW","stlPerG":"0.4","blkPerG":"0.1"},{"name":null,"ppg":null,"apg":null,"rpg":null,"position":null,"age":null,"fgPct":null,"teamId":null,"stlPerG":null,"blkPerG":null},{"name":"LaMelo Ball","ppg":"23.5","apg":"8.2","rpg":"5.2","position":"PG","age":"21","fgPct":".409","teamId":"CHO","stlPerG":"1.1","blkPerG":"0.3"},{"name":"Mo Bamba","ppg":"7.4","apg":"1.0","rpg":"4.8","position":"C","age":"24","fgPct":".495","teamId":"ORL","stlPerG":"0.3","blkPerG":"1.0"},{"name":"Paolo Banchero","ppg":"21.1","apg":"3.8","rpg":"6.6","position":"PF","age":"20","fgPct":".439","teamId":"ORL","stlPerG":"1.1","blkPerG":"0.5"},{"name":"Desmond Bane","ppg":"21.8","apg":"4.0","rpg":"5.0","position":"SG","age":"24","fgPct":".453","teamId":"MEM","stlPerG":"0.8","blkPerG":"0.3"},{"name":"Dalano Banton","ppg":"5.2","apg":"1.2","rpg":"1.5","position":"PG","age":"23","fgPct":".423","teamId":"TOR","stlPerG":"0.5","blkPerG":"0.5"},{"name":"Dominick Barlow","ppg":"2.5","apg":"0.8","rpg":"0.8","position":"SF","age":"19","fgPct":".429","teamId":"SAS","stlPerG":"0.3","blkPerG":"0.0"},{"name":"Harrison Barnes","ppg":"15.3","apg":"1.7","rpg":"5.0","position":"PF","age":"30","fgPct":".482","teamId":"SAC","stlPerG":"0.8","blkPerG":"0.1"},{"name":"Scottie Barnes","ppg":"15.7","apg":"4.7","rpg":"7.2","position":"PF","age":"21","fgPct":".462","teamId":"TOR","stlPerG":"1.1","blkPerG":"0.8"},{"name":"RJ Barrett","ppg":"20.0","apg":"2.9","rpg":"5.5","position":"SG","age":"22","fgPct":".427","teamId":"NYK","stlPerG":"0.5","blkPerG":"0.2"},{"name":"Will Barton","ppg":"7.5","apg":"2.5","rpg":"2.8","position":"SG","age":"32","fgPct":".375","teamId":"WAS","stlPerG":"0.4","blkPerG":"0.3"},{"name":"Charles Bassey","ppg":"4.7","apg":"1.2","rpg":"5.2","position":"C","age":"22","fgPct":".671","teamId":"SAS","stlPerG":"0.3","blkPerG":"0.9"},{"name":"Keita Bates-Diop","ppg":"7.3","apg":"0.7","rpg":"2.7","position":"SF","age":"27","fgPct":".520","teamId":"SAS","stlPerG":"0.6","blkPerG":"0.2"},{"name":"Nicolas Batum","ppg":"6.3","apg":"1.4","rpg":"4.3","position":"PF","age":"34","fgPct":".430","teamId":"LAC","stlPerG":"0.7","blkPerG":"0.7"},{"name":"Darius Bazley","ppg":"5.8","apg":"1.0","rpg":"3.5","position":"PF","age":"22","fgPct":".432","teamId":"OKC","stlPerG":"0.6","blkPerG":"1.0"},{"name":"Bradley Beal","ppg":"22.7","apg":"5.1","rpg":"3.5","position":"SG","age":"29","fgPct":".528","teamId":"WAS","stlPerG":"1.0","blkPerG":"0.6"},{"name":"Malik Beasley","ppg":"13.7","apg":"1.6","rpg":"3.5","position":"SG","age":"26","fgPct":".399","teamId":"UTA","stlPerG":"0.9","blkPerG":"0.2"},{"name":"MarJon Beauchamp","ppg":"6.0","apg":"0.7","rpg":"2.5","position":"SF","age":"22","fgPct":".395","teamId":"MIL","stlPerG":"0.5","blkPerG":"0.1"},{"name":"Dāvis Bertāns","ppg":"4.3","apg":"0.3","rpg":"0.9","position":"PF","age":"30","fgPct":".404","teamId":"DAL","stlPerG":"0.2","blkPerG":"0.1"},{"name":"Patrick Beverley","ppg":"5.9","apg":"2.5","rpg":"3.4","position":"PG","age":"34","fgPct":".391","teamId":"LAL","stlPerG":"0.8","blkPerG":"0.6"},{"name":"Saddiq Bey","ppg":"14.3","apg":"1.5","rpg":"4.4","position":"SF","age":"23","fgPct":".400","teamId":"DET","stlPerG":"1.0","blkPerG":"0.2"},{"name":null,"ppg":null,"apg":null,"rpg":null,"position":null,"age":null,"fgPct":null,"teamId":null,"stlPerG":null,"blkPerG":null},{"name":"Khem Birch","ppg":"2.2","apg":"0.4","rpg":"1.3","position":"C","age":"30","fgPct":".594","teamId":"TOR","stlPerG":"0.3","blkPerG":"0.3"},{"name":"Goga Bitadze","ppg":"3.5","apg":"0.9","rpg":"2.3","position":"C","age":"23","fgPct":".519","teamId":"IND","stlPerG":"0.5","blkPerG":"0.5"},{"name":"Bismack Biyombo","ppg":"3.6","apg":"0.8","rpg":"3.8","position":"C","age":"30","fgPct":".569","teamId":"PHO","stlPerG":"0.3","blkPerG":"1.3"},{"name":"Buddy Boeheim","ppg":"0.0","apg":"0.0","rpg":"0.0","position":"PG","age":"23","fgPct":"","teamId":"DET","stlPerG":"0.0","blkPerG":"0.0"},{"name":"Bogdan Bogdanović","ppg":"15.4","apg":"2.9","rpg":"3.7","position":"SG","age":"30","fgPct":".417","teamId":"ATL","stlPerG":"0.9","blkPerG":"0.3"},{"name":"Bojan Bogdanović","ppg":"21.3","apg":"2.8","rpg":"3.6","position":"PF","age":"33","fgPct":".486","teamId":"DET","stlPerG":"0.6","blkPerG":"0.1"},{"name":"Bol Bol","ppg":"11.9","apg":"0.9","rpg":"6.9","position":"PF","age":"23","fgPct":".585","teamId":"ORL","stlPerG":"0.5","blkPerG":"1.5"},{"name":"Leandro Bolmaro","ppg":"0.5","apg":"0.6","rpg":"0.5","position":"SG","age":"22","fgPct":".176","teamId":"UTA","stlPerG":"0.3","blkPerG":"0.1"},{"name":"Devin Booker","ppg":"27.1","apg":"5.6","rpg":"4.6","position":"SG","age":"26","fgPct":".477","teamId":"PHO","stlPerG":"0.9","blkPerG":"0.4"},{"name":"Brandon Boston Jr.","ppg":"5.5","apg":"0.9","rpg":"1.5","position":"SG","age":"21","fgPct":".365","teamId":"LAC","stlPerG":"0.4","blkPerG":"0.0"},{"name":"Chris Boucher","ppg":"9.4","apg":"0.5","rpg":"5.5","position":"PF","age":"30","fgPct":".468","teamId":"TOR","stlPerG":"0.7","blkPerG":"0.7"},{"name":"James Bouknight","ppg":"4.4","apg":"1.1","rpg":"2.0","position":"SG","age":"22","fgPct":".333","teamId":"CHO","stlPerG":"0.5","blkPerG":"0.2"},{"name":"Tony Bradley","ppg":"1.2","apg":"0.1","rpg":"1.0","position":"C","age":"25","fgPct":".500","teamId":"CHI","stlPerG":"0.1","blkPerG":"0.0"},{"name":"Malaki Branham","ppg":"7.1","apg":"1.6","rpg":"1.7","position":"SF","age":"19","fgPct":".413","teamId":"SAS","stlPerG":"0.4","blkPerG":"0.1"},{"name":"Christian Braun","ppg":"3.1","apg":"0.5","rpg":"1.9","position":"SG","age":"21","fgPct":".437","teamId":"DEN","stlPerG":"0.3","blkPerG":"0.2"},{"name":"Mikal Bridges","ppg":"16.0","apg":"3.5","rpg":"4.5","position":"SF","age":"26","fgPct":".461","teamId":"PHO","stlPerG":"1.1","blkPerG":"0.9"},{"name":"Oshae Brissett","ppg":"6.0","apg":"0.5","rpg":"3.5","position":"SF","age":"24","fgPct":".403","teamId":"IND","stlPerG":"0.6","blkPerG":"0.2"},{"name":"Malcolm Brogdon","ppg":"14.1","apg":"3.7","rpg":"4.2","position":"PG","age":"30","fgPct":".479","teamId":"BOS","stlPerG":"0.6","blkPerG":"0.3"},{"name":"Dillon Brooks","ppg":"16.3","apg":"2.6","rpg":"3.5","position":"SF","age":"27","fgPct":".403","teamId":"MEM","stlPerG":"0.8","blkPerG":"0.2"},{"name":"Bruce Brown","ppg":"11.1","apg":"3.7","rpg":"4.1","position":"SG","age":"26","fgPct":".499","teamId":"DEN","stlPerG":"1.0","blkPerG":"0.7"},{"name":null,"ppg":null,"apg":null,"rpg":null,"position":null,"age":null,"fgPct":null,"teamId":null,"stlPerG":null,"blkPerG":null},{"name":"Greg Brown III","ppg":"2.0","apg":"0.1","rpg":"1.3","position":"PF","age":"21","fgPct":".458","teamId":"POR","stlPerG":"0.3","blkPerG":"0.4"},{"name":"Jaylen Brown","ppg":"26.9","apg":"3.2","rpg":"7.1","position":"SF","age":"26","fgPct":".495","teamId":"BOS","stlPerG":"1.1","blkPerG":"0.5"},{"name":"Kendall Brown","ppg":"1.5","apg":"0.5","rpg":"1.0","position":"SG","age":"19","fgPct":".571","teamId":"IND","stlPerG":"0.7","blkPerG":"0.0"},{"name":"Moses Brown","ppg":"4.3","apg":"0.1","rpg":"3.7","position":"C","age":"23","fgPct":".629","teamId":"LAC","stlPerG":"0.1","blkPerG":"0.4"},{"name":"Sterling Brown","ppg":"0.0","apg":"0.5","rpg":"2.0","position":"SG","age":"27","fgPct":".000","teamId":"LAL","stlPerG":"0.8","blkPerG":"0.0"},{"name":"Troy Brown Jr.","ppg":"6.7","apg":"0.8","rpg":"3.9","position":"SF","age":"23","fgPct":".439","teamId":"LAL","stlPerG":"0.8","blkPerG":"0.2"},{"name":"Jalen Brunson","ppg":"22.6","apg":"6.3","rpg":"3.7","position":"PG","age":"26","fgPct":".470","teamId":"NYK","stlPerG":"1.0","blkPerG":"0.2"},{"name":"Thomas Bryant","ppg":"12.5","apg":"0.8","rpg":"7.0","position":"C","age":"25","fgPct":".642","teamId":"LAL","stlPerG":"0.4","blkPerG":"0.5"},{"name":"Reggie Bullock","ppg":"6.1","apg":"1.2","rpg":"3.4","position":"SF","age":"31","fgPct":".376","teamId":"DAL","stlPerG":"0.7","blkPerG":"0.2"},{"name":"Alec Burks","ppg":"13.6","apg":"2.2","rpg":"3.0","position":"SG","age":"31","fgPct":".456","teamId":"DET","stlPerG":"0.7","blkPerG":"0.1"},{"name":"Jimmy Butler","ppg":"22.0","apg":"5.2","rpg":"6.3","position":"SF","age":"33","fgPct":".514","teamId":"MIA","stlPerG":"2.0","blkPerG":"0.4"},{"name":"John Butler","ppg":"0.5","apg":"0.3","rpg":"0.5","position":"C","age":"20","fgPct":".333","teamId":"POR","stlPerG":"0.0","blkPerG":"0.3"},{"name":"Jamal Cain","ppg":"4.9","apg":"0.6","rpg":"2.9","position":"SF","age":"23","fgPct":".521","teamId":"MIA","stlPerG":"0.6","blkPerG":"0.0"},{"name":"Kentavious Caldwell-Pope","ppg":"11.6","apg":"2.3","rpg":"3.0","position":"SG","age":"29","fgPct":".474","teamId":"DEN","stlPerG":"1.3","blkPerG":"0.3"},{"name":"Facundo Campazzo","ppg":"1.3","apg":"1.1","rpg":"0.3","position":"PG","age":"31","fgPct":".231","teamId":"DAL","stlPerG":"0.8","blkPerG":"0.0"},{"name":"Vlatko Čančar","ppg":"4.9","apg":"1.2","rpg":"2.1","position":"PF","age":"25","fgPct":".500","teamId":"DEN","stlPerG":"0.4","blkPerG":"0.2"},{"name":"Clint Capela","ppg":"12.1","apg":"0.7","rpg":"11.5","position":"C","age":"28","fgPct":".645","teamId":"ATL","stlPerG":"0.6","blkPerG":"1.4"},{"name":"Vernon Carey Jr.","ppg":"0.3","apg":"0.1","rpg":"0.7","position":"C","age":"21","fgPct":".333","teamId":"WAS","stlPerG":"0.1","blkPerG":"0.3"},{"name":"Jevon Carter","ppg":"7.3","apg":"2.8","rpg":"2.7","position":"PG","age":"27","fgPct":".399","teamId":"MIL","stlPerG":"1.1","blkPerG":"0.5"},{"name":"Wendell Carter Jr.","ppg":"15.8","apg":"2.8","rpg":"8.6","position":"C","age":"23","fgPct":".522","teamId":"ORL","stlPerG":"0.4","blkPerG":"0.6"},{"name":null,"ppg":null,"apg":null,"rpg":null,"position":null,"age":null,"fgPct":null,"teamId":null,"stlPerG":null,"blkPerG":null},{"name":"Alex Caruso","ppg":"5.5","apg":"3.5","rpg":"2.9","position":"PG","age":"28","fgPct":".430","teamId":"CHI","stlPerG":"1.7","blkPerG":"0.7"},{"name":"Julian Champagnie","ppg":"0.0","apg":"0.0","rpg":"0.0","position":"SF","age":"21","fgPct":".000","teamId":"PHI","stlPerG":"0.5","blkPerG":"0.0"},{"name":"Justin Champagnie","ppg":"2.0","apg":"0.3","rpg":"1.3","position":"SF","age":"21","fgPct":"1.000","teamId":"TOR","stlPerG":"0.0","blkPerG":"0.0"},{"name":"Kennedy Chandler","ppg":"2.7","apg":"2.1","rpg":"1.4","position":"PG","age":"20","fgPct":".400","teamId":"MEM","stlPerG":"0.5","blkPerG":"0.2"},{"name":"Max Christie","ppg":"3.8","apg":"0.6","rpg":"2.2","position":"SG","age":"19","fgPct":".409","teamId":"LAL","stlPerG":"0.2","blkPerG":"0.1"},{"name":"Josh Christopher","ppg":"2.9","apg":"0.7","rpg":"1.0","position":"SG","age":"21","fgPct":".381","teamId":"HOU","stlPerG":"0.2","blkPerG":"0.1"},{"name":"Brandon Clarke","ppg":"10.1","apg":"1.1","rpg":"5.4","position":"PF","age":"26","fgPct":".654","teamId":"MEM","stlPerG":"0.6","blkPerG":"0.7"},{"name":"Jordan Clarkson","ppg":"21.0","apg":"4.3","rpg":"4.0","position":"SG","age":"30","fgPct":".452","teamId":"UTA","stlPerG":"0.5","blkPerG":"0.2"},{"name":"Nic Claxton","ppg":"12.2","apg":"1.5","rpg":"8.6","position":"C","age":"23","fgPct":".730","teamId":"BRK","stlPerG":"0.8","blkPerG":"2.7"},{"name":"Amir Coffey","ppg":"3.7","apg":"1.3","rpg":"1.2","position":"SG","age":"25","fgPct":".375","teamId":"LAC","stlPerG":"0.2","blkPerG":"0.1"},{"name":"John Collins","ppg":"13.3","apg":"1.3","rpg":"7.8","position":"PF","age":"25","fgPct":".504","teamId":"ATL","stlPerG":"0.7","blkPerG":"1.4"},{"name":"Zach Collins","ppg":"9.2","apg":"2.4","rpg":"5.8","position":"C","age":"25","fgPct":".533","teamId":"SAS","stlPerG":"0.4","blkPerG":"0.7"},{"name":"Mike Conley","ppg":"10.5","apg":"7.5","rpg":"2.3","position":"PG","age":"35","fgPct":".396","teamId":"UTA","stlPerG":"1.0","blkPerG":"0.2"},{"name":"Pat Connaughton","ppg":"8.0","apg":"1.1","rpg":"4.3","position":"SG","age":"30","fgPct":".360","teamId":"MIL","stlPerG":"0.6","blkPerG":"0.1"},{"name":"Robert Covington","ppg":"5.6","apg":"1.3","rpg":"3.9","position":"PF","age":"32","fgPct":".386","teamId":"LAC","stlPerG":"0.6","blkPerG":"0.6"},{"name":"Torrey Craig","ppg":"8.4","apg":"1.5","rpg":"5.7","position":"SF","age":"32","fgPct":".468","teamId":"PHO","stlPerG":"0.7","blkPerG":"0.6"},{"name":"Jarrett Culver","ppg":"4.4","apg":"0.6","rpg":"3.8","position":"SG","age":"23","fgPct":".395","teamId":"ATL","stlPerG":"0.6","blkPerG":"0.2"},{"name":"Cade Cunningham","ppg":"19.9","apg":"6.0","rpg":"6.2","position":"PG","age":"21","fgPct":".415","teamId":"DET","stlPerG":"0.8","blkPerG":"0.6"},{"name":"Seth Curry","ppg":"10.1","apg":"2.0","rpg":"2.2","position":"SG","age":"32","fgPct":".462","teamId":"BRK","stlPerG":"0.7","blkPerG":"0.2"},{"name":"Stephen Curry","ppg":"29.3","apg":"6.3","rpg":"6.4","position":"PG","age":"34","fgPct":".487","teamId":"GSW","stlPerG":"1.0","blkPerG":"0.4"},{"name":null,"ppg":null,"apg":null,"rpg":null,"position":null,"age":null,"fgPct":null,"teamId":null,"stlPerG":null,"blkPerG":null},{"name":"Dyson Daniels","ppg":"4.5","apg":"2.3","rpg":"3.5","position":"PG","age":"19","fgPct":".457","teamId":"NOP","stlPerG":"0.9","blkPerG":"0.2"},{"name":"Anthony Davis","ppg":"27.4","apg":"2.6","rpg":"12.1","position":"C","age":"29","fgPct":".594","teamId":"LAL","stlPerG":"1.3","blkPerG":"2.1"},{"name":"Johnny Davis","ppg":"1.1","apg":"0.2","rpg":"0.7","position":"SG","age":"20","fgPct":".308","teamId":"WAS","stlPerG":"0.0","blkPerG":"0.1"},{"name":"Terence Davis","ppg":"6.5","apg":"1.3","rpg":"2.5","position":"SG","age":"25","fgPct":".420","teamId":"SAC","stlPerG":"0.8","blkPerG":"0.3"},{"name":"JD Davison","ppg":"0.5","apg":"0.3","rpg":"0.5","position":"PG","age":"20","fgPct":".200","teamId":"BOS","stlPerG":"0.3","blkPerG":"0.0"},{"name":"Dewayne Dedmon","ppg":"5.9","apg":"0.5","rpg":"3.7","position":"C","age":"33","fgPct":".512","teamId":"MIA","stlPerG":"0.2","blkPerG":"0.4"},{"name":"Matthew Dellavedova","ppg":"1.4","apg":"1.2","rpg":"0.3","position":"PG","age":"32","fgPct":".385","teamId":"SAC","stlPerG":"0.3","blkPerG":"0.0"},{"name":"DeMar DeRozan","ppg":"26.1","apg":"4.9","rpg":"5.1","position":"SF","age":"33","fgPct":".506","teamId":"CHI","stlPerG":"1.0","blkPerG":"0.5"},{"name":"Moussa Diabaté","ppg":"4.0","apg":"0.2","rpg":"4.2","position":"PF","age":"21","fgPct":".500","teamId":"LAC","stlPerG":"0.4","blkPerG":"0.4"},{"name":"Mamadi Diakite","ppg":"2.0","apg":"0.2","rpg":"0.8","position":"PF","age":"26","fgPct":".478","teamId":"CLE","stlPerG":"0.2","blkPerG":"0.4"},{"name":"Hamidou Diallo","ppg":"8.1","apg":"0.9","rpg":"3.5","position":"SG","age":"24","fgPct":".573","teamId":"DET","stlPerG":"0.8","blkPerG":"0.2"},{"name":"Gorgui Dieng","ppg":"3.8","apg":"1.9","rpg":"3.0","position":"C","age":"33","fgPct":".417","teamId":"SAS","stlPerG":"0.1","blkPerG":"0.5"},{"name":"Ousmane Dieng","ppg":"4.4","apg":"1.4","rpg":"2.9","position":"SF","age":"19","fgPct":".424","teamId":"OKC","stlPerG":"0.4","blkPerG":"0.3"},{"name":"Spencer Dinwiddie","ppg":"16.7","apg":"5.3","rpg":"3.0","position":"PG","age":"29","fgPct":".464","teamId":"DAL","stlPerG":"0.8","blkPerG":"0.3"},{"name":"Donte DiVincenzo","ppg":"7.8","apg":"3.0","rpg":"4.7","position":"SG","age":"26","fgPct":".400","teamId":"GSW","stlPerG":"1.2","blkPerG":"0.1"},{"name":"Luka Dončić","ppg":"33.7","apg":"8.8","rpg":"8.8","position":"PG","age":"23","fgPct":".497","teamId":"DAL","stlPerG":"1.6","blkPerG":"0.6"},{"name":"Tyler Dorsey","ppg":"3.0","apg":"0.0","rpg":"0.7","position":"SG","age":"26","fgPct":".800","teamId":"DAL","stlPerG":"0.0","blkPerG":"0.0"},{"name":"Luguentz Dort","ppg":"14.3","apg":"2.3","rpg":"4.3","position":"SG","age":"23","fgPct":".412","teamId":"OKC","stlPerG":"1.0","blkPerG":"0.3"},{"name":"Ayo Dosunmu","ppg":"9.6","apg":"2.6","rpg":"3.1","position":"SG","age":"23","fgPct":".506","teamId":"CHI","stlPerG":"0.7","blkPerG":"0.3"},{"name":"Devon Dotson","ppg":"0.5","apg":"1.3","rpg":"1.7","position":"PG","age":"23","fgPct":".100","teamId":"WAS","stlPerG":"0.8","blkPerG":"0.0"},{"name":null,"ppg":null,"apg":null,"rpg":null,"position":null,"age":null,"fgPct":null,"teamId":null,"stlPerG":null,"blkPerG":null},{"name":"Jeff Dowtin","ppg":"2.3","apg":"0.9","rpg":"1.1","position":"PG","age":"25","fgPct":".522","teamId":"TOR","stlPerG":"0.2","blkPerG":"0.1"},{"name":"PJ Dozier","ppg":"1.0","apg":"0.0","rpg":"0.3","position":"SG","age":"26","fgPct":".500","teamId":"SAC","stlPerG":"0.3","blkPerG":"0.0"},{"name":"Goran Dragić","ppg":"7.2","apg":"2.8","rpg":"1.5","position":"PG","age":"36","fgPct":".433","teamId":"CHI","stlPerG":"0.2","blkPerG":"0.1"},{"name":"Andre Drummond","ppg":"6.2","apg":"0.7","rpg":"6.8","position":"C","age":"29","fgPct":".601","teamId":"CHI","stlPerG":"0.6","blkPerG":"0.3"},{"name":"Chris Duarte","ppg":"7.1","apg":"1.3","rpg":"2.2","position":"SF","age":"25","fgPct":".333","teamId":"IND","stlPerG":"0.1","blkPerG":"0.2"},{"name":"David Duke Jr.","ppg":"3.0","apg":"0.9","rpg":"1.1","position":"SG","age":"23","fgPct":".442","teamId":"BRK","stlPerG":"0.4","blkPerG":"0.1"},{"name":"Kevin Durant","ppg":"29.7","apg":"5.3","rpg":"6.7","position":"PF","age":"34","fgPct":".559","teamId":"BRK","stlPerG":"0.8","blkPerG":"1.5"},{"name":"Jalen Duren","ppg":"7.8","apg":"1.0","rpg":"8.6","position":"C","age":"19","fgPct":".641","teamId":"DET","stlPerG":"0.6","blkPerG":"0.8"},{"name":"Tari Eason","ppg":"8.0","apg":"0.9","rpg":"5.2","position":"PF","age":"21","fgPct":".433","teamId":"HOU","stlPerG":"1.1","blkPerG":"0.5"},{"name":"Anthony Edwards","ppg":"23.7","apg":"4.4","rpg":"6.0","position":"SG","age":"21","fgPct":".454","teamId":"MIN","stlPerG":"1.7","blkPerG":"0.5"},{"name":"Kessler Edwards","ppg":"1.2","apg":"0.2","rpg":"1.1","position":"SF","age":"22","fgPct":".273","teamId":"BRK","stlPerG":"0.2","blkPerG":"0.1"},{"name":"Keon Ellis","ppg":"0.6","apg":"0.2","rpg":"0.4","position":"SG","age":"23","fgPct":".500","teamId":"SAC","stlPerG":"0.0","blkPerG":"0.0"},{"name":"Joel Embiid","ppg":"33.6","apg":"4.2","rpg":"9.8","position":"C","age":"28","fgPct":".537","teamId":"PHI","stlPerG":"1.0","blkPerG":"1.7"},{"name":"Drew Eubanks","ppg":"5.6","apg":"1.0","rpg":"4.3","position":"C","age":"25","fgPct":".730","teamId":"POR","stlPerG":"0.5","blkPerG":"1.1"},{"name":"Bruno Fernando","ppg":"3.6","apg":"1.0","rpg":"3.5","position":"C","age":"24","fgPct":".554","teamId":"HOU","stlPerG":"0.2","blkPerG":"0.7"},{"name":"Dorian Finney-Smith","ppg":"8.4","apg":"1.2","rpg":"4.2","position":"PF","age":"29","fgPct":".398","teamId":"DAL","stlPerG":"0.9","blkPerG":"0.5"},{"name":"Malachi Flynn","ppg":"5.4","apg":"1.5","rpg":"1.6","position":"PG","age":"24","fgPct":".376","teamId":"TOR","stlPerG":"0.3","blkPerG":"0.1"},{"name":"Simone Fontecchio","ppg":"3.6","apg":"0.3","rpg":"1.1","position":"SF","age":"27","fgPct":".372","teamId":"UTA","stlPerG":"0.1","blkPerG":"0.2"},{"name":"Bryn Forbes","ppg":"3.3","apg":"0.6","rpg":"0.6","position":"SG","age":"29","fgPct":".338","teamId":"MIN","stlPerG":"0.3","blkPerG":"0.0"},{"name":"Trent Forrest","ppg":"3.1","apg":"1.9","rpg":"1.7","position":"PG","age":"24","fgPct":".478","teamId":"ATL","stlPerG":"0.4","blkPerG":"0.1"},{"name":null,"ppg":null,"apg":null,"rpg":null,"position":null,"age":null,"fgPct":null,"teamId":null,"stlPerG":null,"blkPerG":null},{"name":"Michael Foster Jr.","ppg":"0.0","apg":"0.0","rpg":"0.0","position":"PF","age":"20","fgPct":"","teamId":"PHI","stlPerG":"0.0","blkPerG":"0.0"},{"name":"Evan Fournier","ppg":"6.7","apg":"1.5","rpg":"2.1","position":"SG","age":"30","fgPct":".350","teamId":"NYK","stlPerG":"0.6","blkPerG":"0.2"},{"name":"De'Aaron Fox","ppg":"24.0","apg":"6.0","rpg":"4.3","position":"PG","age":"25","fgPct":".507","teamId":"SAC","stlPerG":"0.9","blkPerG":"0.4"},{"name":"Markelle Fultz","ppg":"12.2","apg":"5.6","rpg":"4.1","position":"PG","age":"24","fgPct":".502","teamId":"ORL","stlPerG":"1.7","blkPerG":"0.3"},{"name":"Wenyen Gabriel","ppg":"6.7","apg":"0.5","rpg":"4.1","position":"PF","age":"25","fgPct":".627","teamId":"LAL","stlPerG":"0.4","blkPerG":"0.7"},{"name":"Daniel Gafford","ppg":"7.8","apg":"0.6","rpg":"4.8","position":"C","age":"24","fgPct":".751","teamId":"WAS","stlPerG":"0.3","blkPerG":"1.1"},{"name":"Darius Garland","ppg":"21.5","apg":"8.0","rpg":"2.9","position":"PG","age":"23","fgPct":".447","teamId":"CLE","stlPerG":"1.2","blkPerG":"0.1"},{"name":"Usman Garuba","ppg":"3.1","apg":"1.0","rpg":"4.7","position":"PF","age":"20","fgPct":".520","teamId":"HOU","stlPerG":"0.7","blkPerG":"0.5"},{"name":"Luka Garza","ppg":"6.1","apg":"0.4","rpg":"2.0","position":"C","age":"24","fgPct":".525","teamId":"MIN","stlPerG":"0.1","blkPerG":"0.1"},{"name":"Rudy Gay","ppg":"4.2","apg":"0.8","rpg":"2.9","position":"PF","age":"36","fgPct":".351","teamId":"UTA","stlPerG":"0.5","blkPerG":"0.4"},{"name":"Paul George","ppg":"23.4","apg":"5.1","rpg":"6.0","position":"SF","age":"32","fgPct":".451","teamId":"LAC","stlPerG":"1.5","blkPerG":"0.4"},{"name":"Taj Gibson","ppg":"3.6","apg":"0.6","rpg":"1.8","position":"C","age":"37","fgPct":".543","teamId":"WAS","stlPerG":"0.4","blkPerG":"0.3"},{"name":"Josh Giddey","ppg":"16.0","apg":"5.9","rpg":"8.0","position":"SG","age":"20","fgPct":".483","teamId":"OKC","stlPerG":"0.7","blkPerG":"0.5"},{"name":"Shai Gilgeous-Alexander","ppg":"30.5","apg":"5.5","rpg":"4.9","position":"PG","age":"24","fgPct":".501","teamId":"OKC","stlPerG":"1.7","blkPerG":"1.1"},{"name":"Anthony Gill","ppg":"3.0","apg":"0.4","rpg":"1.4","position":"PF","age":"30","fgPct":".594","teamId":"WAS","stlPerG":"0.1","blkPerG":"0.1"},{"name":"Rudy Gobert","ppg":"13.3","apg":"0.8","rpg":"11.5","position":"C","age":"30","fgPct":".679","teamId":"MIN","stlPerG":"0.8","blkPerG":"1.3"},{"name":"Jordan Goodwin","ppg":"6.7","apg":"2.7","rpg":"3.5","position":"PG","age":"24","fgPct":".462","teamId":"WAS","stlPerG":"1.0","blkPerG":"0.5"},{"name":"Aaron Gordon","ppg":"16.5","apg":"2.6","rpg":"6.8","position":"PF","age":"27","fgPct":".588","teamId":"DEN","stlPerG":"0.8","blkPerG":"0.8"},{"name":"Eric Gordon","ppg":"12.2","apg":"2.6","rpg":"1.9","position":"SG","age":"34","fgPct":".427","teamId":"HOU","stlPerG":"0.5","blkPerG":"0.4"},{"name":"Devonte' Graham","ppg":"5.0","apg":"2.2","rpg":"1.5","position":"PG","age":"27","fgPct":".352","teamId":"NOP","stlPerG":"0.5","blkPerG":"0.2"},{"name":null,"ppg":null,"apg":null,"rpg":null,"position":null,"age":null,"fgPct":null,"teamId":null,"stlPerG":null,"blkPerG":null},{"name":"Jerami Grant","ppg":"21.7","apg":"2.4","rpg":"4.3","position":"PF","age":"28","fgPct":".494","teamId":"POR","stlPerG":"0.9","blkPerG":"0.8"},{"name":"A.J. Green","ppg":"4.8","apg":"0.5","rpg":"1.1","position":"SG","age":"23","fgPct":".468","teamId":"MIL","stlPerG":"0.2","blkPerG":"0.0"},{"name":"Draymond Green","ppg":"8.0","apg":"6.8","rpg":"7.1","position":"PF","age":"32","fgPct":".504","teamId":"GSW","stlPerG":"0.9","blkPerG":"0.8"},{"name":"Jalen Green","ppg":"21.9","apg":"3.6","rpg":"4.3","position":"SG","age":"20","fgPct":".413","teamId":"HOU","stlPerG":"0.8","blkPerG":"0.2"},{"name":"JaMychal Green","ppg":"5.8","apg":"0.8","rpg":"4.0","position":"PF","age":"32","fgPct":".512","teamId":"GSW","stlPerG":"0.5","blkPerG":"0.4"},{"name":"Javonte Green","ppg":"5.9","apg":"0.8","rpg":"2.9","position":"SG","age":"29","fgPct":".587","teamId":"CHI","stlPerG":"0.8","blkPerG":"0.7"},{"name":"Jeff Green","ppg":"7.5","apg":"1.1","rpg":"2.8","position":"PF","age":"36","fgPct":".527","teamId":"DEN","stlPerG":"0.4","blkPerG":"0.3"},{"name":"Josh Green","ppg":"7.1","apg":"1.2","rpg":"2.2","position":"SG","age":"22","fgPct":".594","teamId":"DAL","stlPerG":"0.9","blkPerG":"0.0"},{"name":"AJ Griffin","ppg":"9.9","apg":"1.0","rpg":"2.2","position":"SF","age":"19","fgPct":".485","teamId":"ATL","stlPerG":"0.8","blkPerG":"0.1"},{"name":"Blake Griffin","ppg":"4.8","apg":"1.2","rpg":"3.6","position":"C","age":"33","fgPct":".492","teamId":"BOS","stlPerG":"0.3","blkPerG":"0.1"},{"name":"Quentin Grimes","ppg":"10.5","apg":"2.0","rpg":"3.5","position":"SG","age":"22","fgPct":".452","teamId":"NYK","stlPerG":"0.8","blkPerG":"0.4"},{"name":"Rui Hachimura","ppg":"12.4","apg":"1.2","rpg":"4.2","position":"PF","age":"24","fgPct":".480","teamId":"WAS","stlPerG":"0.4","blkPerG":"0.3"},{"name":"Tyrese Haliburton","ppg":"20.2","apg":"10.2","rpg":"4.0","position":"PG","age":"22","fgPct":".480","teamId":"IND","stlPerG":"1.8","blkPerG":"0.4"},{"name":"Jordan Hall","ppg":"3.1","apg":"1.2","rpg":"1.3","position":"SF","age":"21","fgPct":".321","teamId":"SAS","stlPerG":"0.1","blkPerG":"0.0"},{"name":"R.J. Hampton","ppg":"6.0","apg":"1.4","rpg":"1.6","position":"PG","age":"21","fgPct":".439","teamId":"ORL","stlPerG":"0.6","blkPerG":"0.2"},{"name":"Tim Hardaway Jr.","ppg":"14.0","apg":"1.5","rpg":"3.2","position":"SG","age":"30","fgPct":".390","teamId":"DAL","stlPerG":"0.8","blkPerG":"0.1"},{"name":"James Harden","ppg":"21.5","apg":"11.2","rpg":"6.5","position":"PG","age":"33","fgPct":".447","teamId":"PHI","stlPerG":"1.3","blkPerG":"0.6"},{"name":"Jaden Hardy","ppg":"6.3","apg":"0.6","rpg":"1.2","position":"SG","age":"20","fgPct":".416","teamId":"DAL","stlPerG":"0.2","blkPerG":"0.2"},{"name":"Ron Harper Jr.","ppg":"3.0","apg":"0.0","rpg":"0.5","position":"SF","age":"22","fgPct":".500","teamId":"TOR","stlPerG":"0.0","blkPerG":"0.0"},{"name":"Montrezl Harrell","ppg":"5.8","apg":"0.6","rpg":"2.8","position":"C","age":"29","fgPct":".583","teamId":"PHI","stlPerG":"0.3","blkPerG":"0.6"},{"name":null,"ppg":null,"apg":null,"rpg":null,"position":null,"age":null,"fgPct":null,"teamId":null,"stlPerG":null,"blkPerG":null},{"name":"Gary Harris","ppg":"8.4","apg":"1.3","rpg":"2.3","position":"SG","age":"28","fgPct":".457","teamId":"ORL","stlPerG":"0.8","blkPerG":"0.2"},{"name":"Joe Harris","ppg":"8.2","apg":"1.5","rpg":"2.8","position":"SG","age":"31","fgPct":".443","teamId":"BRK","stlPerG":"0.6","blkPerG":"0.3"},{"name":"Kevon Harris","ppg":"3.7","apg":"0.5","rpg":"2.0","position":"SG","age":"25","fgPct":".421","teamId":"ORL","stlPerG":"0.5","blkPerG":"0.1"},{"name":"Tobias Harris","ppg":"16.3","apg":"2.6","rpg":"6.3","position":"PF","age":"30","fgPct":".499","teamId":"PHI","stlPerG":"1.1","blkPerG":"0.6"},{"name":"Josh Hart","ppg":"9.5","apg":"4.0","rpg":"8.3","position":"SF","age":"27","fgPct":".498","teamId":"POR","stlPerG":"1.1","blkPerG":"0.2"},{"name":"Isaiah Hartenstein","ppg":"5.1","apg":"0.7","rpg":"6.1","position":"C","age":"24","fgPct":".485","teamId":"NYK","stlPerG":"0.6","blkPerG":"0.7"},{"name":"Udonis Haslem","ppg":"0.6","apg":"0.0","rpg":"1.2","position":"C","age":"42","fgPct":".100","teamId":"MIA","stlPerG":"0.2","blkPerG":"0.2"},{"name":"Sam Hauser","ppg":"5.6","apg":"0.7","rpg":"2.4","position":"PF","age":"25","fgPct":".440","teamId":"BOS","stlPerG":"0.3","blkPerG":"0.2"},{"name":"Jaxson Hayes","ppg":"4.7","apg":"0.8","rpg":"2.8","position":"C","age":"22","fgPct":".512","teamId":"NOP","stlPerG":"0.3","blkPerG":"0.4"},{"name":"Killian Hayes","ppg":"9.8","apg":"5.8","rpg":"2.8","position":"PG","age":"21","fgPct":".389","teamId":"DET","stlPerG":"1.3","blkPerG":"0.4"},{"name":"Gordon Hayward","ppg":"13.7","apg":"3.9","rpg":"4.7","position":"SF","age":"32","fgPct":".423","teamId":"CHO","stlPerG":"0.8","blkPerG":"0.2"},{"name":"Juancho Hernangómez","ppg":"3.6","apg":"0.6","rpg":"3.3","position":"PF","age":"27","fgPct":".452","teamId":"TOR","stlPerG":"0.5","blkPerG":"0.2"},{"name":"Willy Hernangómez","ppg":"6.9","apg":"0.9","rpg":"4.6","position":"C","age":"28","fgPct":".521","teamId":"NOP","stlPerG":"0.3","blkPerG":"0.3"},{"name":"Tyler Herro","ppg":"20.8","apg":"4.5","rpg":"5.9","position":"SG","age":"23","fgPct":".445","teamId":"MIA","stlPerG":"1.0","blkPerG":"0.3"},{"name":"Buddy Hield","ppg":"17.6","apg":"2.7","rpg":"4.8","position":"SF","age":"30","fgPct":".449","teamId":"IND","stlPerG":"1.0","blkPerG":"0.3"},{"name":"Haywood Highsmith","ppg":"4.5","apg":"0.7","rpg":"3.8","position":"SF","age":"26","fgPct":".399","teamId":"MIA","stlPerG":"0.8","blkPerG":"0.3"},{"name":"George Hill","ppg":"5.2","apg":"2.6","rpg":"2.0","position":"PG","age":"36","fgPct":".450","teamId":"MIL","stlPerG":"0.5","blkPerG":"0.1"},{"name":"Malcolm Hill","ppg":"0.0","apg":"0.0","rpg":"0.3","position":"SF","age":"27","fgPct":"","teamId":"CHI","stlPerG":"0.0","blkPerG":"0.0"},{"name":"Aaron Holiday","ppg":"4.5","apg":"1.5","rpg":"1.4","position":"PG","age":"26","fgPct":".416","teamId":"ATL","stlPerG":"0.6","blkPerG":"0.2"},{"name":"Jrue Holiday","ppg":"19.4","apg":"7.4","rpg":"4.9","position":"PG","age":"32","fgPct":".467","teamId":"MIL","stlPerG":"1.4","blkPerG":"0.4"},{"name":null,"ppg":null,"apg":null,"rpg":null,"position":null,"age":null,"fgPct":null,"teamId":null,"stlPerG":null,"blkPerG":null},{"name":"Justin Holiday","ppg":"4.5","apg":"0.9","rpg":"0.9","position":"SG","age":"33","fgPct":".377","teamId":"ATL","stlPerG":"0.2","blkPerG":"0.4"},{"name":"Richaun Holmes","ppg":"3.3","apg":"0.2","rpg":"2.3","position":"C","age":"29","fgPct":".690","teamId":"SAC","stlPerG":"0.1","blkPerG":"0.3"},{"name":"Al Horford","ppg":"9.8","apg":"2.6","rpg":"6.3","position":"C","age":"36","fgPct":".494","teamId":"BOS","stlPerG":"0.5","blkPerG":"1.0"},{"name":"Talen Horton-Tucker","ppg":"6.9","apg":"2.3","rpg":"2.4","position":"SG","age":"22","fgPct":".398","teamId":"UTA","stlPerG":"0.7","blkPerG":"0.3"},{"name":"Danuel House Jr.","ppg":"4.7","apg":"0.8","rpg":"1.9","position":"SF","age":"29","fgPct":".469","teamId":"PHI","stlPerG":"0.2","blkPerG":"0.2"},{"name":"Caleb Houstan","ppg":"4.0","apg":"0.6","rpg":"2.3","position":"SF","age":"20","fgPct":".381","teamId":"ORL","stlPerG":"0.2","blkPerG":"0.1"},{"name":"Trevor Hudgins","ppg":"3.0","apg":"0.0","rpg":"0.0","position":"PG","age":"23","fgPct":"1.000","teamId":"HOU","stlPerG":"0.0","blkPerG":"0.0"},{"name":"Kevin Huerter","ppg":"15.7","apg":"3.1","rpg":"3.3","position":"SG","age":"24","fgPct":".481","teamId":"SAC","stlPerG":"1.1","blkPerG":"0.3"},{"name":"De'Andre Hunter","ppg":"15.5","apg":"1.3","rpg":"4.4","position":"SF","age":"25","fgPct":".453","teamId":"ATL","stlPerG":"0.4","blkPerG":"0.2"},{"name":"Bones Hyland","ppg":"12.8","apg":"3.1","rpg":"2.2","position":"PG","age":"22","fgPct":".406","teamId":"DEN","stlPerG":"0.6","blkPerG":"0.3"},{"name":"Serge Ibaka","ppg":"4.1","apg":"0.3","rpg":"2.8","position":"C","age":"33","fgPct":".481","teamId":"MIL","stlPerG":"0.1","blkPerG":"0.4"},{"name":"Andre Iguodala","ppg":"2.3","apg":"1.7","rpg":"2.3","position":"SF","age":"39","fgPct":".750","teamId":"GSW","stlPerG":"0.3","blkPerG":"0.3"},{"name":"Joe Ingles","ppg":"6.8","apg":"4.0","rpg":"2.3","position":"SF","age":"35","fgPct":".375","teamId":"MIL","stlPerG":"0.5","blkPerG":"0.2"},{"name":"Brandon Ingram","ppg":"20.8","apg":"4.7","rpg":"5.1","position":"SF","age":"25","fgPct":".472","teamId":"NOP","stlPerG":"0.9","blkPerG":"0.7"},{"name":"Kyrie Irving","ppg":"25.8","apg":"4.9","rpg":"4.9","position":"PG","age":"30","fgPct":".477","teamId":"BRK","stlPerG":"0.9","blkPerG":"0.9"},{"name":"Jaden Ivey","ppg":"15.2","apg":"4.3","rpg":"4.1","position":"SG","age":"20","fgPct":".412","teamId":"DET","stlPerG":"0.9","blkPerG":"0.2"},{"name":"Isaiah Jackson","ppg":"7.1","apg":"0.9","rpg":"4.2","position":"C","age":"21","fgPct":".556","teamId":"IND","stlPerG":"0.5","blkPerG":"1.4"},{"name":"Jaren Jackson Jr.","ppg":"16.5","apg":"1.0","rpg":"6.8","position":"C","age":"23","fgPct":".513","teamId":"MEM","stlPerG":"1.1","blkPerG":"3.3"},{"name":"Justin Jackson","ppg":"0.8","apg":"0.4","rpg":"0.5","position":"SF","age":"27","fgPct":".227","teamId":"BOS","stlPerG":"0.2","blkPerG":"0.2"},{"name":"Reggie Jackson","ppg":"11.0","apg":"3.7","rpg":"2.4","position":"PG","age":"32","fgPct":".412","teamId":"LAC","stlPerG":"0.7","blkPerG":"0.1"},{"name":null,"ppg":null,"apg":null,"rpg":null,"position":null,"age":null,"fgPct":null,"teamId":null,"stlPerG":null,"blkPerG":null},{"name":"LeBron James","ppg":"29.8","apg":"7.0","rpg":"8.4","position":"PF","age":"38","fgPct":".509","teamId":"LAL","stlPerG":"1.0","blkPerG":"0.5"},{"name":"Ty Jerome","ppg":"6.7","apg":"2.4","rpg":"1.6","position":"SG","age":"25","fgPct":".486","teamId":"GSW","stlPerG":"0.4","blkPerG":"0.1"},{"name":"Isaiah Joe","ppg":"7.5","apg":"1.1","rpg":"2.1","position":"SG","age":"23","fgPct":".468","teamId":"OKC","stlPerG":"0.6","blkPerG":"0.1"},{"name":"Alize Johnson","ppg":"1.8","apg":"0.3","rpg":"2.5","position":"PF","age":"26","fgPct":".500","teamId":"SAS","stlPerG":"0.3","blkPerG":"0.0"},{"name":"Cameron Johnson","ppg":"13.7","apg":"1.8","rpg":"3.7","position":"PF","age":"26","fgPct":".441","teamId":"PHO","stlPerG":"1.1","blkPerG":"0.6"},{"name":"Jalen Johnson","ppg":"5.4","apg":"1.0","rpg":"3.5","position":"SF","age":"21","fgPct":".481","teamId":"ATL","stlPerG":"0.5","blkPerG":"0.5"},{"name":"James Johnson","ppg":"1.8","apg":"0.6","rpg":"1.2","position":"PF","age":"35","fgPct":".360","teamId":"IND","stlPerG":"0.3","blkPerG":"0.5"},{"name":"Keldon Johnson","ppg":"21.5","apg":"2.6","rpg":"4.9","position":"SF","age":"23","fgPct":".421","teamId":"SAS","stlPerG":"0.7","blkPerG":"0.2"},{"name":"Keon Johnson","ppg":"4.5","apg":"1.0","rpg":"1.5","position":"SG","age":"20","fgPct":".358","teamId":"POR","stlPerG":"0.5","blkPerG":"0.2"},{"name":"Stanley Johnson","ppg":"5.9","apg":"2.4","rpg":"2.6","position":"SF","age":"26","fgPct":".565","teamId":"SAS","stlPerG":"0.4","blkPerG":"0.2"},{"name":"Nikola Jokić","ppg":"25.1","apg":"9.9","rpg":"11.0","position":"C","age":"27","fgPct":".626","teamId":"DEN","stlPerG":"1.4","blkPerG":"0.6"},{"name":"Carlik Jones","ppg":"2.0","apg":"0.0","rpg":"0.0","position":"PG","age":"25","fgPct":"1.000","teamId":"CHI","stlPerG":"0.0","blkPerG":"0.0"},{"name":"Damian Jones","ppg":"2.9","apg":"0.2","rpg":"2.8","position":"C","age":"27","fgPct":".556","teamId":"LAL","stlPerG":"0.2","blkPerG":"0.6"},{"name":"Derrick Jones Jr.","ppg":"5.9","apg":"0.6","rpg":"2.5","position":"SF","age":"25","fgPct":".533","teamId":"CHI","stlPerG":"0.4","blkPerG":"0.7"},{"name":"Herbert Jones","ppg":"10.0","apg":"2.1","rpg":"3.7","position":"SF","age":"24","fgPct":".426","teamId":"NOP","stlPerG":"1.5","blkPerG":"0.7"},{"name":"Kai Jones","ppg":"2.7","apg":"0.2","rpg":"2.0","position":"C","age":"22","fgPct":".500","teamId":"CHO","stlPerG":"0.2","blkPerG":"0.4"},{"name":"Tre Jones","ppg":"13.8","apg":"6.4","rpg":"3.8","position":"PG","age":"23","fgPct":".446","teamId":"SAS","stlPerG":"1.3","blkPerG":"0.2"},{"name":"Tyus Jones","ppg":"10.6","apg":"4.8","rpg":"2.3","position":"PG","age":"26","fgPct":".441","teamId":"MEM","stlPerG":"1.0","blkPerG":"0.0"},{"name":"DeAndre Jordan","ppg":"4.7","apg":"0.8","rpg":"5.1","position":"C","age":"34","fgPct":".772","teamId":"DEN","stlPerG":"0.2","blkPerG":"0.6"},{"name":"Cory Joseph","ppg":"4.6","apg":"3.1","rpg":"1.3","position":"PG","age":"31","fgPct":".392","teamId":"DET","stlPerG":"0.4","blkPerG":"0.1"},{"name":null,"ppg":null,"apg":null,"rpg":null,"position":null,"age":null,"fgPct":null,"teamId":null,"stlPerG":null,"blkPerG":null},{"name":"Nikola Jović","ppg":"5.5","apg":"0.7","rpg":"2.1","position":"PF","age":"19","fgPct":".406","teamId":"MIA","stlPerG":"0.5","blkPerG":"0.1"},{"name":"Mfiondu Kabengele","ppg":"2.0","apg":"0.0","rpg":"4.0","position":"PF","age":"25","fgPct":".500","teamId":"BOS","stlPerG":"0.0","blkPerG":"0.0"},{"name":"Frank Kaminsky","ppg":"3.0","apg":"0.9","rpg":"1.6","position":"C","age":"29","fgPct":".575","teamId":"ATL","stlPerG":"0.1","blkPerG":"0.0"},{"name":"Trevor Keels","ppg":"0.0","apg":"0.0","rpg":"1.0","position":"SG","age":"19","fgPct":".000","teamId":"NYK","stlPerG":"0.0","blkPerG":"0.0"},{"name":"Luke Kennard","ppg":"8.7","apg":"1.2","rpg":"2.5","position":"SG","age":"26","fgPct":".489","teamId":"LAC","stlPerG":"0.6","blkPerG":"0.1"},{"name":"Walker Kessler","ppg":"7.6","apg":"0.8","rpg":"7.2","position":"C","age":"21","fgPct":".715","teamId":"UTA","stlPerG":"0.3","blkPerG":"2.0"},{"name":"Braxton Key","ppg":"1.3","apg":"0.0","rpg":"0.3","position":"SF","age":"25","fgPct":"1.000","teamId":"DET","stlPerG":"0.0","blkPerG":"0.0"},{"name":"Corey Kispert","ppg":"9.4","apg":"1.4","rpg":"2.8","position":"SF","age":"23","fgPct":".478","teamId":"WAS","stlPerG":"0.6","blkPerG":"0.1"},{"name":"Maxi Kleber","ppg":"6.2","apg":"1.0","rpg":"3.5","position":"C","age":"31","fgPct":".490","teamId":"DAL","stlPerG":"0.3","blkPerG":"1.0"},{"name":"Nathan Knight","ppg":"3.1","apg":"0.3","rpg":"1.4","position":"PF","age":"25","fgPct":".641","teamId":"MIN","stlPerG":"0.2","blkPerG":"0.1"},{"name":"Kevin Knox","ppg":"6.0","apg":"0.4","rpg":"2.4","position":"PF","age":"23","fgPct":".467","teamId":"DET","stlPerG":"0.3","blkPerG":"0.3"},{"name":"Christian Koloko","ppg":"3.8","apg":"0.5","rpg":"3.4","position":"C","age":"22","fgPct":".492","teamId":"TOR","stlPerG":"0.3","blkPerG":"1.1"},{"name":"John Konchar","ppg":"6.8","apg":"1.5","rpg":"5.2","position":"SG","age":"26","fgPct":".447","teamId":"MEM","stlPerG":"1.1","blkPerG":"0.3"},{"name":"Furkan Korkmaz","ppg":"4.0","apg":"0.8","rpg":"1.2","position":"SG","age":"25","fgPct":".410","teamId":"PHI","stlPerG":"0.3","blkPerG":"0.1"},{"name":"Luke Kornet","ppg":"3.8","apg":"0.7","rpg":"3.1","position":"C","age":"27","fgPct":".696","teamId":"BOS","stlPerG":"0.2","blkPerG":"0.8"},{"name":"Vit Krejci","ppg":"1.5","apg":"0.6","rpg":"0.6","position":"PG","age":"22","fgPct":".385","teamId":"ATL","stlPerG":"0.1","blkPerG":"0.1"},{"name":"Jonathan Kuminga","ppg":"7.5","apg":"1.7","rpg":"3.2","position":"PF","age":"20","fgPct":".472","teamId":"GSW","stlPerG":"0.5","blkPerG":"0.5"},{"name":"Kyle Kuzma","ppg":"21.7","apg":"4.0","rpg":"7.6","position":"PF","age":"27","fgPct":".457","teamId":"WAS","stlPerG":"0.5","blkPerG":"0.4"},{"name":"Anthony Lamb","ppg":"7.5","apg":"1.7","rpg":"3.4","position":"SF","age":"25","fgPct":".513","teamId":"GSW","stlPerG":"0.6","blkPerG":"0.3"},{"name":"Jock Landale","ppg":"6.6","apg":"0.9","rpg":"3.9","position":"C","age":"27","fgPct":".517","teamId":"PHO","stlPerG":"0.2","blkPerG":"0.6"},{"name":null,"ppg":null,"apg":null,"rpg":null,"position":null,"age":null,"fgPct":null,"teamId":null,"stlPerG":null,"blkPerG":null},{"name":"Romeo Langford","ppg":"7.1","apg":"1.2","rpg":"2.7","position":"SG","age":"23","fgPct":".473","teamId":"SAS","stlPerG":"0.5","blkPerG":"0.3"},{"name":"Jake LaRavia","ppg":"3.6","apg":"0.8","rpg":"2.2","position":"PF","age":"21","fgPct":".405","teamId":"MEM","stlPerG":"0.4","blkPerG":"0.2"},{"name":"Zach LaVine","ppg":"24.1","apg":"4.3","rpg":"4.6","position":"SG","age":"27","fgPct":".463","teamId":"CHI","stlPerG":"1.0","blkPerG":"0.2"},{"name":"A.J. Lawson","ppg":"1.4","apg":"0.1","rpg":"0.5","position":"SG","age":"22","fgPct":".400","teamId":null,"stlPerG":"0.0","blkPerG":"0.0"},{"name":"A.J. Lawson","ppg":"2.0","apg":"0.0","rpg":"1.0","position":"SG","age":"22","fgPct":"1.000","teamId":"MIN","stlPerG":"0.0","blkPerG":"0.0"},{"name":"A.J. Lawson","ppg":"1.3","apg":"0.1","rpg":"0.4","position":"SG","age":"22","fgPct":".333","teamId":"DAL","stlPerG":"0.0","blkPerG":"0.0"},{"name":"Damion Lee","ppg":"9.3","apg":"1.5","rpg":"3.5","position":"SG","age":"30","fgPct":".463","teamId":"PHO","stlPerG":"0.4","blkPerG":"0.1"},{"name":"Saben Lee","ppg":"8.5","apg":"2.8","rpg":"1.7","position":"PG","age":"23","fgPct":".548","teamId":null,"stlPerG":"0.5","blkPerG":"0.0"},{"name":"Saben Lee","ppg":"3.0","apg":"1.0","rpg":"0.0","position":"PG","age":"23","fgPct":".750","teamId":"PHI","stlPerG":"0.5","blkPerG":"0.0"},{"name":"Saben Lee","ppg":"11.3","apg":"3.8","rpg":"2.5","position":"PG","age":"23","fgPct":".519","teamId":"PHO","stlPerG":"0.5","blkPerG":"0.0"},{"name":"Alex Len","ppg":"1.3","apg":"0.3","rpg":"1.3","position":"C","age":"29","fgPct":".500","teamId":"SAC","stlPerG":"0.0","blkPerG":"0.0"},{"name":"Kawhi Leonard","ppg":"19.4","apg":"3.7","rpg":"6.1","position":"SF","age":"31","fgPct":".482","teamId":"LAC","stlPerG":"1.1","blkPerG":"0.4"},{"name":"Caris LeVert","ppg":"12.5","apg":"3.7","rpg":"4.0","position":"SG","age":"28","fgPct":".418","teamId":"CLE","stlPerG":"0.8","blkPerG":"0.2"},{"name":"Kira Lewis Jr.","ppg":"4.7","apg":"0.3","rpg":"1.0","position":"PG","age":"21","fgPct":".500","teamId":"NOP","stlPerG":"0.2","blkPerG":"0.0"},{"name":"Damian Lillard","ppg":"29.2","apg":"7.2","rpg":"3.9","position":"PG","age":"32","fgPct":".449","teamId":"POR","stlPerG":"0.9","blkPerG":"0.4"},{"name":"Nassir Little","ppg":"5.8","apg":"0.8","rpg":"2.4","position":"SF","age":"22","fgPct":".472","teamId":"POR","stlPerG":"0.4","blkPerG":"0.2"},{"name":"Isaiah Livers","ppg":"5.8","apg":"0.7","rpg":"2.5","position":"PF","age":"24","fgPct":".407","teamId":"DET","stlPerG":"0.4","blkPerG":"0.5"},{"name":"Kenneth Lofton Jr.","ppg":"2.5","apg":"0.7","rpg":"0.7","position":"PF","age":"20","fgPct":".467","teamId":"MEM","stlPerG":"0.0","blkPerG":"0.0"},{"name":"Kevon Looney","ppg":"6.6","apg":"2.8","rpg":"8.5","position":"C","age":"26","fgPct":".637","teamId":"GSW","stlPerG":"0.4","blkPerG":"0.5"},{"name":"Brook Lopez","ppg":"14.6","apg":"1.2","rpg":"6.3","position":"C","age":"34","fgPct":".506","teamId":"MIL","stlPerG":"0.5","blkPerG":"2.5"},{"name":"Robin Lopez","ppg":"3.0","apg":"0.4","rpg":"1.5","position":"C","age":"34","fgPct":".640","teamId":"CLE","stlPerG":"0.0","blkPerG":"0.1"},{"name":"Kevin Love","ppg":"8.7","apg":"1.9","rpg":"7.1","position":"PF","age":"34","fgPct":".382","teamId":"CLE","stlPerG":"0.2","blkPerG":"0.2"},{"name":"Kyle Lowry","ppg":"12.9","apg":"5.6","rpg":"4.5","position":"PG","age":"36","fgPct":".401","teamId":"MIA","stlPerG":"1.1","blkPerG":"0.5"},{"name":"Trey Lyles","ppg":"7.0","apg":"0.8","rpg":"3.7","position":"PF","age":"27","fgPct":".468","teamId":"SAC","stlPerG":"0.3","blkPerG":"0.5"},{"name":null,"ppg":null,"apg":null,"rpg":null,"position":null,"age":null,"fgPct":null,"teamId":null,"stlPerG":null,"blkPerG":null},{"name":"Théo Maledon","ppg":"5.5","apg":"2.5","rpg":"2.4","position":"PG","age":"21","fgPct":".408","teamId":"CHO","stlPerG":"0.8","blkPerG":"0.2"},{"name":"Sandro Mamukelashvili","ppg":"2.3","apg":"0.7","rpg":"2.3","position":"C","age":"23","fgPct":".333","teamId":"MIL","stlPerG":"0.1","blkPerG":"0.2"},{"name":"Terance Mann","ppg":"8.7","apg":"2.0","rpg":"3.7","position":"SG","age":"26","fgPct":".517","teamId":"LAC","stlPerG":"0.6","blkPerG":"0.3"},{"name":"Tre Mann","ppg":"8.3","apg":"1.7","rpg":"2.4","position":"PG","age":"21","fgPct":".390","teamId":"OKC","stlPerG":"0.7","blkPerG":"0.2"},{"name":"Boban Marjanović","ppg":"2.7","apg":"0.2","rpg":"1.5","position":"C","age":"34","fgPct":".682","teamId":"HOU","stlPerG":"0.1","blkPerG":"0.1"},{"name":"Lauri Markkanen","ppg":"24.8","apg":"1.8","rpg":"8.7","position":"SF","age":"25","fgPct":".520","teamId":"UTA","stlPerG":"0.6","blkPerG":"0.6"},{"name":"Naji Marshall","ppg":"10.5","apg":"2.5","rpg":"3.7","position":"SF","age":"25","fgPct":".436","teamId":"NOP","stlPerG":"0.8","blkPerG":"0.2"},{"name":"Caleb Martin","ppg":"10.3","apg":"1.8","rpg":"4.8","position":"PF","age":"27","fgPct":".461","teamId":"MIA","stlPerG":"1.1","blkPerG":"0.4"},{"name":"Cody Martin","ppg":"5.0","apg":"1.6","rpg":"3.4","position":"SF","age":"27","fgPct":".389","teamId":"CHO","stlPerG":"0.6","blkPerG":"0.1"},{"name":"Kenyon Martin Jr.","ppg":"11.0","apg":"1.4","rpg":"5.0","position":"SF","age":"22","fgPct":".549","teamId":"HOU","stlPerG":"0.4","blkPerG":"0.3"},{"name":"Tyrese Martin","ppg":"1.4","apg":"0.0","rpg":"0.5","position":"SG","age":"23","fgPct":".375","teamId":"ATL","stlPerG":"0.1","blkPerG":"0.0"},{"name":"Garrison Mathews","ppg":"4.7","apg":"0.5","rpg":"1.3","position":"SG","age":"26","fgPct":".352","teamId":"HOU","stlPerG":"0.6","blkPerG":"0.1"},{"name":"Bennedict Mathurin","ppg":"17.1","apg":"1.4","rpg":"4.0","position":"SF","age":"20","fgPct":".422","teamId":"IND","stlPerG":"0.6","blkPerG":"0.1"},{"name":"Wesley Matthews","ppg":"2.9","apg":"0.6","rpg":"1.6","position":"SG","age":"36","fgPct":".329","teamId":"MIL","stlPerG":"0.5","blkPerG":"0.2"},{"name":"Tyrese Maxey","ppg":"20.7","apg":"3.7","rpg":"3.0","position":"SG","age":"22","fgPct":".459","teamId":"PHI","stlPerG":"0.9","blkPerG":"0.2"},{"name":"Miles McBride","ppg":"3.4","apg":"1.1","rpg":"0.8","position":"PG","age":"22","fgPct":".333","teamId":"NYK","stlPerG":"0.6","blkPerG":"0.0"},{"name":"CJ McCollum","ppg":"21.3","apg":"5.8","rpg":"4.6","position":"SG","age":"31","fgPct":".435","teamId":"NOP","stlPerG":"1.0","blkPerG":"0.6"},{"name":"T.J. McConnell","ppg":"6.7","apg":"4.6","rpg":"2.6","position":"PG","age":"30","fgPct":".498","teamId":"IND","stlPerG":"1.1","blkPerG":"0.1"},{"name":"Jaden McDaniels","ppg":"11.7","apg":"2.0","rpg":"3.8","position":"PF","age":"22","fgPct":".527","teamId":"MIN","stlPerG":"1.1","blkPerG":"1.1"},{"name":"Jalen McDaniels","ppg":"11.2","apg":"2.0","rpg":"4.7","position":"SF","age":"25","fgPct":".463","teamId":"CHO","stlPerG":"1.2","blkPerG":"0.6"},{"name":null,"ppg":null,"apg":null,"rpg":null,"position":null,"age":null,"fgPct":null,"teamId":null,"stlPerG":null,"blkPerG":null},{"name":"Doug McDermott","ppg":"10.3","apg":"1.5","rpg":"2.5","position":"SF","age":"31","fgPct":".482","teamId":"SAS","stlPerG":"0.2","blkPerG":"0.2"},{"name":"JaVale McGee","ppg":"3.9","apg":"0.3","rpg":"2.4","position":"C","age":"35","fgPct":".620","teamId":"DAL","stlPerG":"0.1","blkPerG":"0.6"},{"name":"Bryce McGowens","ppg":"3.5","apg":"0.9","rpg":"1.4","position":"SG","age":"20","fgPct":".415","teamId":"CHO","stlPerG":"0.2","blkPerG":"0.2"},{"name":"Rodney McGruder","ppg":"3.2","apg":"0.6","rpg":"1.4","position":"SG","age":"31","fgPct":".365","teamId":"DET","stlPerG":"0.3","blkPerG":"0.0"},{"name":"Jordan McLaughlin","ppg":"4.1","apg":"3.6","rpg":"1.7","position":"PG","age":"26","fgPct":".424","teamId":"MIN","stlPerG":"0.8","blkPerG":"0.1"},{"name":"De'Anthony Melton","ppg":"10.9","apg":"2.9","rpg":"4.5","position":"PG","age":"24","fgPct":".417","teamId":"PHI","stlPerG":"1.9","blkPerG":"0.5"},{"name":"Chimezie Metu","ppg":"5.1","apg":"0.7","rpg":"3.2","position":"C","age":"25","fgPct":".596","teamId":"SAC","stlPerG":"0.3","blkPerG":"0.2"},{"name":"Khris Middleton","ppg":"11.1","apg":"4.4","rpg":"2.6","position":"SF","age":"31","fgPct":".325","teamId":"MIL","stlPerG":"0.6","blkPerG":"0.1"},{"name":"Patty Mills","ppg":"5.5","apg":"1.2","rpg":"1.0","position":"PG","age":"34","fgPct":".451","teamId":"BRK","stlPerG":"0.3","blkPerG":"0.0"},{"name":"Shake Milton","ppg":"10.2","apg":"3.3","rpg":"2.9","position":"SG","age":"26","fgPct":".506","teamId":"PHI","stlPerG":"0.3","blkPerG":"0.2"},{"name":"Josh Minott","ppg":"1.4","apg":"0.3","rpg":"0.7","position":"SF","age":"20","fgPct":".600","teamId":"MIN","stlPerG":"0.1","blkPerG":"0.3"},{"name":"Davion Mitchell","ppg":"6.1","apg":"2.2","rpg":"1.5","position":"PG","age":"24","fgPct":".464","teamId":"SAC","stlPerG":"0.5","blkPerG":"0.3"},{"name":"Donovan Mitchell","ppg":"28.4","apg":"4.8","rpg":"3.9","position":"SG","age":"26","fgPct":".484","teamId":"CLE","stlPerG":"1.4","blkPerG":"0.4"},{"name":"Evan Mobley","ppg":"14.5","apg":"2.7","rpg":"8.9","position":"PF","age":"21","fgPct":".557","teamId":"CLE","stlPerG":"0.8","blkPerG":"1.3"},{"name":"Isaiah Mobley","ppg":"1.1","apg":"0.0","rpg":"1.4","position":"PF","age":"23","fgPct":".500","teamId":"CLE","stlPerG":"0.1","blkPerG":"0.0"},{"name":"Chima Moneke","ppg":"1.0","apg":"0.5","rpg":"1.0","position":"SF","age":"27","fgPct":".500","teamId":"SAC","stlPerG":"0.0","blkPerG":"0.0"},{"name":"Malik Monk","ppg":"13.5","apg":"3.8","rpg":"2.4","position":"SG","age":"24","fgPct":".431","teamId":"SAC","stlPerG":"0.6","blkPerG":"0.2"},{"name":"Moses Moody","ppg":"5.2","apg":"0.9","rpg":"1.6","position":"SG","age":"20","fgPct":".451","teamId":"GSW","stlPerG":"0.3","blkPerG":"0.1"},{"name":"Wendell Moore Jr.","ppg":"1.7","apg":"0.5","rpg":"0.7","position":"SG","age":"21","fgPct":".419","teamId":"MIN","stlPerG":"0.3","blkPerG":"0.2"},{"name":"Ja Morant","ppg":"27.4","apg":"7.9","rpg":"5.6","position":"PG","age":"23","fgPct":".469","teamId":"MEM","stlPerG":"1.0","blkPerG":"0.3"},{"name":null,"ppg":null,"apg":null,"rpg":null,"position":null,"age":null,"fgPct":null,"teamId":null,"stlPerG":null,"blkPerG":null},{"name":"Marcus Morris","ppg":"13.1","apg":"1.8","rpg":"4.6","position":"PF","age":"33","fgPct":".435","teamId":"LAC","stlPerG":"0.7","blkPerG":"0.4"},{"name":"Markieff Morris","ppg":"4.0","apg":"1.0","rpg":"2.2","position":"PF","age":"33","fgPct":".420","teamId":"BRK","stlPerG":"0.3","blkPerG":"0.2"},{"name":"Monte Morris","ppg":"10.3","apg":"5.4","rpg":"3.4","position":"PG","age":"27","fgPct":".467","teamId":"WAS","stlPerG":"0.7","blkPerG":"0.2"},{"name":"Trey Murphy III","ppg":"12.5","apg":"1.4","rpg":"3.8","position":"SF","age":"22","fgPct":".476","teamId":"NOP","stlPerG":"1.0","blkPerG":"0.5"},{"name":"Dejounte Murray","ppg":"20.6","apg":"6.1","rpg":"5.5","position":"SG","age":"26","fgPct":".455","teamId":"ATL","stlPerG":"1.7","blkPerG":"0.3"},{"name":"Jamal Murray","ppg":"18.8","apg":"5.4","rpg":"4.0","position":"PG","age":"25","fgPct":".448","teamId":"DEN","stlPerG":"0.9","blkPerG":"0.2"},{"name":"Keegan Murray","ppg":"11.7","apg":"0.9","rpg":"4.0","position":"SF","age":"22","fgPct":".434","teamId":"SAC","stlPerG":"0.8","blkPerG":"0.6"},{"name":"Mike Muscala","ppg":"5.7","apg":"0.9","rpg":"3.1","position":"C","age":"31","fgPct":".422","teamId":"OKC","stlPerG":"0.3","blkPerG":"0.5"},{"name":"Svi Mykhailiuk","ppg":"1.8","apg":"0.1","rpg":"0.6","position":"SF","age":"25","fgPct":".500","teamId":"NYK","stlPerG":"0.1","blkPerG":"0.0"},{"name":"Larry Nance Jr.","ppg":"7.6","apg":"1.9","rpg":"5.5","position":"PF","age":"30","fgPct":".616","teamId":"NOP","stlPerG":"0.9","blkPerG":"0.7"},{"name":"Andrew Nembhard","ppg":"8.6","apg":"4.0","rpg":"3.1","position":"SG","age":"23","fgPct":".442","teamId":"IND","stlPerG":"1.0","blkPerG":"0.2"},{"name":"Aaron Nesmith","ppg":"9.5","apg":"1.2","rpg":"3.8","position":"SF","age":"23","fgPct":".423","teamId":"IND","stlPerG":"0.7","blkPerG":"0.4"},{"name":"Raul Neto","ppg":"3.1","apg":"1.3","rpg":"0.9","position":"PG","age":"30","fgPct":".524","teamId":"CLE","stlPerG":"0.4","blkPerG":"0.0"},{"name":"Georges Niang","ppg":"9.2","apg":"1.1","rpg":"2.3","position":"PF","age":"29","fgPct":".449","teamId":"PHI","stlPerG":"0.4","blkPerG":"0.2"},{"name":"Daishen Nix","ppg":"3.3","apg":"2.4","rpg":"1.5","position":"PG","age":"20","fgPct":".355","teamId":"HOU","stlPerG":"0.7","blkPerG":"0.1"},{"name":"Zeke Nnaji","ppg":"4.9","apg":"0.2","rpg":"1.9","position":"PF","age":"22","fgPct":".603","teamId":"DEN","stlPerG":"0.2","blkPerG":"0.3"},{"name":"Nerlens Noel","ppg":"2.4","apg":"0.6","rpg":"2.8","position":"C","age":"28","fgPct":".444","teamId":"DET","stlPerG":"1.1","blkPerG":"0.8"},{"name":"Jaylen Nowell","ppg":"11.4","apg":"2.2","rpg":"2.6","position":"SG","age":"23","fgPct":".445","teamId":"MIN","stlPerG":"0.7","blkPerG":"0.1"},{"name":"Frank Ntilikina","ppg":"2.9","apg":"1.3","rpg":"1.5","position":"PG","age":"24","fgPct":".364","teamId":"DAL","stlPerG":"0.3","blkPerG":"0.1"},{"name":"Kendrick Nunn","ppg":"6.6","apg":"0.9","rpg":"1.2","position":"SG","age":"27","fgPct":".407","teamId":"LAL","stlPerG":"0.3","blkPerG":"0.1"},{"name":null,"ppg":null,"apg":null,"rpg":null,"position":null,"age":null,"fgPct":null,"teamId":null,"stlPerG":null,"blkPerG":null},{"name":"Jusuf Nurkić","ppg":"14.3","apg":"2.9","rpg":"10.0","position":"C","age":"28","fgPct":".520","teamId":"POR","stlPerG":"0.9","blkPerG":"1.0"},{"name":"Jordan Nwora","ppg":"6.6","apg":"1.0","rpg":"3.2","position":"SF","age":"24","fgPct":".382","teamId":"MIL","stlPerG":"0.3","blkPerG":"0.2"},{"name":"Royce O'Neale","ppg":"9.2","apg":"4.1","rpg":"4.9","position":"SF","age":"29","fgPct":".393","teamId":"BRK","stlPerG":"0.9","blkPerG":"0.7"},{"name":"Chuma Okeke","ppg":"5.4","apg":"1.4","rpg":"4.2","position":"SF","age":"24","fgPct":".368","teamId":"ORL","stlPerG":"0.6","blkPerG":"0.5"},{"name":"Josh Okogie","ppg":"4.8","apg":"1.1","rpg":"2.9","position":"SG","age":"24","fgPct":".411","teamId":"PHO","stlPerG":"0.6","blkPerG":"0.4"},{"name":"Onyeka Okongwu","ppg":"9.3","apg":"1.0","rpg":"7.5","position":"C","age":"22","fgPct":".620","teamId":"ATL","stlPerG":"0.7","blkPerG":"1.2"},{"name":"Isaac Okoro","ppg":"5.8","apg":"0.8","rpg":"2.5","position":"SF","age":"22","fgPct":".475","teamId":"CLE","stlPerG":"0.7","blkPerG":"0.4"},{"name":"KZ Okpala","ppg":"1.5","apg":"0.4","rpg":"1.1","position":"PF","age":"23","fgPct":".457","teamId":"SAC","stlPerG":"0.2","blkPerG":"0.2"},{"name":"Victor Oladipo","ppg":"11.6","apg":"4.0","rpg":"3.5","position":"SG","age":"30","fgPct":".410","teamId":"MIA","stlPerG":"1.7","blkPerG":"0.3"},{"name":"Kelly Olynyk","ppg":"12.2","apg":"3.3","rpg":"5.0","position":"C","age":"31","fgPct":".503","teamId":"UTA","stlPerG":"1.1","blkPerG":"0.6"},{"name":"Eugene Omoruyi","ppg":"5.2","apg":"0.6","rpg":"2.3","position":"SF","age":"25","fgPct":".482","teamId":"OKC","stlPerG":"0.7","blkPerG":"0.0"},{"name":"Cedi Osman","ppg":"8.9","apg":"1.5","rpg":"2.3","position":"SF","age":"27","fgPct":".462","teamId":"CLE","stlPerG":"0.5","blkPerG":"0.1"},{"name":"Kelly Oubre Jr.","ppg":"20.2","apg":"1.2","rpg":"5.1","position":"SF","age":"27","fgPct":".421","teamId":"CHO","stlPerG":"1.6","blkPerG":"0.4"},{"name":"Chris Paul","ppg":"13.1","apg":"8.3","rpg":"4.2","position":"PG","age":"37","fgPct":".425","teamId":"PHO","stlPerG":"1.5","blkPerG":"0.3"},{"name":"Cameron Payne","ppg":"12.1","apg":"5.3","rpg":"2.3","position":"PG","age":"28","fgPct":".412","teamId":"PHO","stlPerG":"0.9","blkPerG":"0.2"},{"name":"Gary Payton II","ppg":"4.0","apg":"2.0","rpg":"2.7","position":"PG","age":"30","fgPct":".714","teamId":"POR","stlPerG":"1.2","blkPerG":"0.0"},{"name":"Theo Pinson","ppg":"1.8","apg":"0.6","rpg":"1.2","position":"SG","age":"27","fgPct":".353","teamId":"DAL","stlPerG":"0.1","blkPerG":"0.0"},{"name":"Scotty Pippen Jr.","ppg":"2.2","apg":"0.2","rpg":"0.8","position":"PG","age":"22","fgPct":".300","teamId":"LAL","stlPerG":"0.4","blkPerG":"0.2"},{"name":"Mason Plumlee","ppg":"11.5","apg":"3.6","rpg":"9.8","position":"C","age":"32","fgPct":".659","teamId":"CHO","stlPerG":"0.7","blkPerG":"0.7"},{"name":"Jakob Poeltl","ppg":"12.3","apg":"2.9","rpg":"9.4","position":"C","age":"27","fgPct":".634","teamId":"SAS","stlPerG":"0.8","blkPerG":"1.3"},{"name":null,"ppg":null,"apg":null,"rpg":null,"position":null,"age":null,"fgPct":null,"teamId":null,"stlPerG":null,"blkPerG":null},{"name":"Aleksej Pokusevski","ppg":"8.8","apg":"2.0","rpg":"5.1","position":"PF","age":"21","fgPct":".440","teamId":"OKC","stlPerG":"0.6","blkPerG":"1.3"},{"name":"Jordan Poole","ppg":"21.1","apg":"4.4","rpg":"2.7","position":"PG","age":"23","fgPct":".435","teamId":"GSW","stlPerG":"0.8","blkPerG":"0.2"},{"name":"Kevin Porter Jr.","ppg":"19.2","apg":"5.6","rpg":"5.5","position":"PG","age":"22","fgPct":".437","teamId":"HOU","stlPerG":"1.3","blkPerG":"0.4"},{"name":"Michael Porter Jr.","ppg":"16.1","apg":"1.1","rpg":"5.6","position":"SF","age":"24","fgPct":".473","teamId":"DEN","stlPerG":"0.6","blkPerG":"0.5"},{"name":"Otto Porter Jr.","ppg":"5.5","apg":"1.0","rpg":"2.4","position":"SF","age":"29","fgPct":".500","teamId":"TOR","stlPerG":"1.4","blkPerG":"0.0"},{"name":"Bobby Portis","ppg":"14.2","apg":"1.8","rpg":"10.0","position":"PF","age":"27","fgPct":".493","teamId":"MIL","stlPerG":"0.5","blkPerG":"0.2"},{"name":"Kristaps Porziņģis","ppg":"22.2","apg":"2.4","rpg":"8.8","position":"C","age":"27","fgPct":".471","teamId":"WAS","stlPerG":"1.0","blkPerG":"1.5"},{"name":"Micah Potter","ppg":"1.3","apg":"0.7","rpg":"1.0","position":"PF","age":"24","fgPct":"1.000","teamId":"UTA","stlPerG":"0.0","blkPerG":"0.0"},{"name":"Dwight Powell","ppg":"6.0","apg":"0.6","rpg":"3.7","position":"C","age":"31","fgPct":".736","teamId":"DAL","stlPerG":"0.5","blkPerG":"0.4"},{"name":"Norman Powell","ppg":"16.0","apg":"1.7","rpg":"2.9","position":"SG","age":"29","fgPct":".474","teamId":"LAC","stlPerG":"0.8","blkPerG":"0.4"},{"name":"Jason Preston","ppg":"2.4","apg":"1.6","rpg":"1.5","position":"PG","age":"23","fgPct":".385","teamId":"LAC","stlPerG":"0.1","blkPerG":"0.0"},{"name":"Joshua Primo","ppg":"7.0","apg":"4.5","rpg":"3.3","position":"SG","age":"20","fgPct":".346","teamId":"SAS","stlPerG":"0.3","blkPerG":"0.5"},{"name":"Taurean Prince","ppg":"8.9","apg":"1.3","rpg":"2.3","position":"SF","age":"28","fgPct":".503","teamId":"MIN","stlPerG":"0.4","blkPerG":"0.3"},{"name":"Payton Pritchard","ppg":"4.5","apg":"0.9","rpg":"1.4","position":"PG","age":"25","fgPct":".406","teamId":"BOS","stlPerG":"0.3","blkPerG":"0.0"},{"name":"Trevelin Queen","ppg":"4.5","apg":"1.0","rpg":"3.5","position":"SG","age":"25","fgPct":".316","teamId":"IND","stlPerG":"0.5","blkPerG":"1.3"},{"name":"Neemias Queta","ppg":"3.0","apg":"0.3","rpg":"2.3","position":"C","age":"23","fgPct":".750","teamId":"SAC","stlPerG":"0.0","blkPerG":"0.3"},{"name":"Immanuel Quickley","ppg":"12.5","apg":"3.2","rpg":"4.0","position":"PG","age":"23","fgPct":".422","teamId":"NYK","stlPerG":"0.9","blkPerG":"0.1"},{"name":"Julius Randle","ppg":"24.2","apg":"3.9","rpg":"10.7","position":"PF","age":"28","fgPct":".455","teamId":"NYK","stlPerG":"0.7","blkPerG":"0.4"},{"name":"Austin Reaves","ppg":"10.8","apg":"2.2","rpg":"3.1","position":"SG","age":"24","fgPct":".488","teamId":"LAL","stlPerG":"0.6","blkPerG":"0.4"},{"name":"Cam Reddish","ppg":"8.4","apg":"1.0","rpg":"1.6","position":"SF","age":"23","fgPct":".449","teamId":"NYK","stlPerG":"0.8","blkPerG":"0.4"},{"name":null,"ppg":null,"apg":null,"rpg":null,"position":null,"age":null,"fgPct":null,"teamId":null,"stlPerG":null,"blkPerG":null},{"name":"Davon Reed","ppg":"2.3","apg":"0.6","rpg":"1.4","position":"SG","age":"27","fgPct":".323","teamId":"DEN","stlPerG":"0.3","blkPerG":"0.1"},{"name":"Paul Reed","ppg":"3.1","apg":"0.4","rpg":"3.3","position":"C","age":"23","fgPct":".560","teamId":"PHI","stlPerG":"0.7","blkPerG":"0.6"},{"name":"Naz Reid","ppg":"10.5","apg":"0.9","rpg":"4.9","position":"C","age":"23","fgPct":".543","teamId":"MIN","stlPerG":"0.5","blkPerG":"0.9"},{"name":"Jared Rhoden","ppg":"2.0","apg":"0.0","rpg":"1.0","position":"SG","age":"23","fgPct":".333","teamId":"DET","stlPerG":"0.0","blkPerG":"0.0"},{"name":"Nick Richards","ppg":"8.3","apg":"0.6","rpg":"5.8","position":"C","age":"25","fgPct":".625","teamId":"CHO","stlPerG":"0.2","blkPerG":"0.8"},{"name":"Josh Richardson","ppg":"11.2","apg":"3.2","rpg":"2.5","position":"SG","age":"29","fgPct":".442","teamId":"SAS","stlPerG":"0.9","blkPerG":"0.2"},{"name":"Austin Rivers","ppg":"5.7","apg":"1.5","rpg":"1.7","position":"SG","age":"30","fgPct":".470","teamId":"MIN","stlPerG":"0.6","blkPerG":"0.1"},{"name":"Duncan Robinson","ppg":"6.9","apg":"1.2","rpg":"1.9","position":"SF","age":"28","fgPct":".368","teamId":"MIA","stlPerG":"0.3","blkPerG":"0.0"},{"name":"Mitchell Robinson","ppg":"7.2","apg":"1.0","rpg":"8.9","position":"C","age":"24","fgPct":".674","teamId":"NYK","stlPerG":"0.9","blkPerG":"1.8"},{"name":"Orlando Robinson","ppg":"5.1","apg":"0.9","rpg":"4.3","position":"C","age":"22","fgPct":".557","teamId":"MIA","stlPerG":"0.6","blkPerG":"0.4"},{"name":"Jeremiah Robinson-Earl","ppg":"8.5","apg":"1.0","rpg":"5.0","position":"PF","age":"22","fgPct":".489","teamId":"OKC","stlPerG":"0.7","blkPerG":"0.4"},{"name":"Isaiah Roby","ppg":"3.8","apg":"1.0","rpg":"2.4","position":"PF","age":"24","fgPct":".440","teamId":"SAS","stlPerG":"0.4","blkPerG":"0.2"},{"name":"David Roddy","ppg":"6.6","apg":"0.7","rpg":"2.8","position":"PF","age":"21","fgPct":".415","teamId":"MEM","stlPerG":"0.4","blkPerG":"0.3"},{"name":"Ryan Rollins","ppg":"1.9","apg":"0.5","rpg":"1.0","position":"PG","age":"20","fgPct":".350","teamId":"GSW","stlPerG":"0.1","blkPerG":"0.1"},{"name":"Derrick Rose","ppg":"5.8","apg":"1.8","rpg":"1.5","position":"PG","age":"34","fgPct":".394","teamId":"NYK","stlPerG":"0.3","blkPerG":"0.2"},{"name":"Terrence Ross","ppg":"8.0","apg":"1.3","rpg":"2.1","position":"SG","age":"31","fgPct":".429","teamId":"ORL","stlPerG":"0.6","blkPerG":"0.2"},{"name":"Terry Rozier","ppg":"21.0","apg":"5.3","rpg":"4.1","position":"SG","age":"28","fgPct":".413","teamId":"CHO","stlPerG":"0.8","blkPerG":"0.2"},{"name":"Ricky Rubio","ppg":"5.3","apg":"1.5","rpg":"2.5","position":"PG","age":"32","fgPct":".350","teamId":"CLE","stlPerG":"0.0","blkPerG":"0.0"},{"name":"D'Angelo Russell","ppg":"17.2","apg":"6.2","rpg":"2.9","position":"PG","age":"26","fgPct":".463","teamId":"MIN","stlPerG":"1.1","blkPerG":"0.5"},{"name":"Matt Ryan","ppg":"3.5","apg":"0.4","rpg":"0.9","position":"SF","age":"25","fgPct":".341","teamId":null,"stlPerG":"0.2","blkPerG":"0.0"},{"name":"Matt Ryan","ppg":"3.9","apg":"0.3","rpg":"1.2","position":"SF","age":"25","fgPct":".306","teamId":"LAL","stlPerG":"0.2","blkPerG":"0.0"},{"name":"Matt Ryan","ppg":"3.1","apg":"0.5","rpg":"0.6","position":"SF","age":"25","fgPct":".394","teamId":"MIN","stlPerG":"0.2","blkPerG":"0.1"},{"name":null,"ppg":null,"apg":null,"rpg":null,"position":null,"age":null,"fgPct":null,"teamId":null,"stlPerG":null,"blkPerG":null},{"name":"Domantas Sabonis","ppg":"18.9","apg":"7.1","rpg":"12.6","position":"C","age":"26","fgPct":".610","teamId":"SAC","stlPerG":"0.8","blkPerG":"0.5"},{"name":"Dario Šarić","ppg":"5.1","apg":"1.4","rpg":"3.2","position":"PF","age":"28","fgPct":".415","teamId":"PHO","stlPerG":"0.3","blkPerG":"0.1"},{"name":"Jordan Schakel","ppg":"1.5","apg":"0.5","rpg":"0.0","position":"SF","age":"24","fgPct":".500","teamId":"WAS","stlPerG":"0.5","blkPerG":"0.0"},{"name":"Admiral Schofield","ppg":"4.9","apg":"0.9","rpg":"2.1","position":"PF","age":"25","fgPct":".478","teamId":"ORL","stlPerG":"0.2","blkPerG":"0.1"},{"name":"Dennis Schröder","ppg":"12.0","apg":"3.6","rpg":"2.2","position":"PG","age":"29","fgPct":".429","teamId":"LAL","stlPerG":"0.6","blkPerG":"0.0"},{"name":"Dereon Seabron","ppg":"1.0","apg":"0.0","rpg":"0.3","position":"SG","age":"22","fgPct":".500","teamId":"NOP","stlPerG":"0.0","blkPerG":"0.0"},{"name":"Alperen Şengün","ppg":"15.1","apg":"3.2","rpg":"8.8","position":"C","age":"20","fgPct":".566","teamId":"HOU","stlPerG":"0.8","blkPerG":"1.0"},{"name":"Collin Sexton","ppg":"14.3","apg":"2.9","rpg":"2.3","position":"SG","age":"24","fgPct":".493","teamId":"UTA","stlPerG":"0.6","blkPerG":"0.1"},{"name":"Landry Shamet","ppg":"9.5","apg":"2.2","rpg":"1.7","position":"SG","age":"25","fgPct":".380","teamId":"PHO","stlPerG":"0.6","blkPerG":"0.2"},{"name":"Day'Ron Sharpe","ppg":"3.4","apg":"0.7","rpg":"3.0","position":"C","age":"21","fgPct":".526","teamId":"BRK","stlPerG":"0.1","blkPerG":"0.6"},{"name":"Shaedon Sharpe","ppg":"7.5","apg":"0.5","rpg":"2.5","position":"SG","age":"19","fgPct":".469","teamId":"POR","stlPerG":"0.3","blkPerG":"0.2"},{"name":"Pascal Siakam","ppg":"25.1","apg":"6.4","rpg":"8.2","position":"C","age":"28","fgPct":".475","teamId":"TOR","stlPerG":"0.8","blkPerG":"0.6"},{"name":"Ben Simmons","ppg":"7.5","apg":"6.3","rpg":"6.8","position":"PG","age":"26","fgPct":".577","teamId":"BRK","stlPerG":"1.5","blkPerG":"0.6"},{"name":"Marko Simonovic","ppg":"0.0","apg":"0.0","rpg":"0.0","position":"C","age":"23","fgPct":".000","teamId":"CHI","stlPerG":"0.0","blkPerG":"0.0"},{"name":"Anfernee Simons","ppg":"21.6","apg":"4.0","rpg":"2.8","position":"SG","age":"23","fgPct":".439","teamId":"POR","stlPerG":"0.7","blkPerG":"0.3"},{"name":"Jericho Sims","ppg":"3.5","apg":"0.4","rpg":"4.2","position":"C","age":"24","fgPct":".771","teamId":"NYK","stlPerG":"0.2","blkPerG":"0.6"},{"name":"Marcus Smart","ppg":"11.4","apg":"7.3","rpg":"3.5","position":"PG","age":"28","fgPct":".420","teamId":"BOS","stlPerG":"1.3","blkPerG":"0.4"},{"name":"Dennis Smith Jr.","ppg":"8.1","apg":"4.9","rpg":"2.8","position":"PG","age":"25","fgPct":".418","teamId":"CHO","stlPerG":"1.6","blkPerG":"0.5"},{"name":"Dru Smith","ppg":"2.2","apg":"1.0","rpg":"1.8","position":"SG","age":"25","fgPct":".357","teamId":"MIA","stlPerG":"0.8","blkPerG":"0.6"},{"name":"Ish Smith","ppg":"2.3","apg":"1.7","rpg":"0.8","position":"PG","age":"34","fgPct":".396","teamId":"DEN","stlPerG":"0.3","blkPerG":"0.3"},{"name":null,"ppg":null,"apg":null,"rpg":null,"position":null,"age":null,"fgPct":null,"teamId":null,"stlPerG":null,"blkPerG":null},{"name":"Jabari Smith Jr.","ppg":"12.0","apg":"1.0","rpg":"6.9","position":"PF","age":"19","fgPct":".391","teamId":"HOU","stlPerG":"0.5","blkPerG":"0.9"},{"name":"Jalen Smith","ppg":"9.8","apg":"1.1","rpg":"6.0","position":"PF","age":"22","fgPct":".460","teamId":"IND","stlPerG":"0.4","blkPerG":"0.9"},{"name":"Jeremy Sochan","ppg":"9.0","apg":"2.4","rpg":"4.8","position":"PF","age":"19","fgPct":".458","teamId":"SAS","stlPerG":"0.8","blkPerG":"0.5"},{"name":"Jaden Springer","ppg":"2.4","apg":"0.1","rpg":"1.0","position":"SG","age":"20","fgPct":".583","teamId":"PHI","stlPerG":"0.3","blkPerG":"0.3"},{"name":"Lamar Stevens","ppg":"5.9","apg":"0.6","rpg":"3.5","position":"PF","age":"25","fgPct":".439","teamId":"CLE","stlPerG":"0.4","blkPerG":"0.5"},{"name":"Isaiah Stewart","ppg":"11.6","apg":"1.2","rpg":"8.1","position":"C","age":"21","fgPct":".447","teamId":"DET","stlPerG":"0.4","blkPerG":"0.7"},{"name":"Max Strus","ppg":"13.2","apg":"2.3","rpg":"3.6","position":"SF","age":"26","fgPct":".403","teamId":"MIA","stlPerG":"0.7","blkPerG":"0.2"},{"name":"Jalen Suggs","ppg":"10.4","apg":"4.3","rpg":"3.0","position":"PG","age":"21","fgPct":".410","teamId":"ORL","stlPerG":"1.3","blkPerG":"0.6"},{"name":"Edmond Sumner","ppg":"6.7","apg":"1.4","rpg":"1.5","position":"SG","age":"27","fgPct":".458","teamId":"BRK","stlPerG":"0.8","blkPerG":"0.2"},{"name":"Cole Swider","ppg":"2.3","apg":"1.0","rpg":"1.5","position":"SF","age":"23","fgPct":".375","teamId":"LAL","stlPerG":"0.0","blkPerG":"0.0"},{"name":"Jae'Sean Tate","ppg":"6.4","apg":"3.2","rpg":"3.3","position":"SF","age":"27","fgPct":".404","teamId":"HOU","stlPerG":"1.0","blkPerG":"0.2"},{"name":"Jayson Tatum","ppg":"31.2","apg":"4.3","rpg":"8.5","position":"PF","age":"24","fgPct":".468","teamId":"BOS","stlPerG":"1.1","blkPerG":"0.8"},{"name":"Terry Taylor","ppg":"2.1","apg":"0.3","rpg":"1.4","position":"SG","age":"23","fgPct":".432","teamId":"IND","stlPerG":"0.1","blkPerG":"0.2"},{"name":"Garrett Temple","ppg":"2.5","apg":"0.5","rpg":"0.7","position":"SG","age":"36","fgPct":".419","teamId":"NOP","stlPerG":"0.6","blkPerG":"0.1"},{"name":"Dalen Terry","ppg":"0.9","apg":"0.4","rpg":"0.4","position":"SG","age":"20","fgPct":".400","teamId":"CHI","stlPerG":"0.1","blkPerG":"0.1"},{"name":"Cam Thomas","ppg":"7.0","apg":"1.3","rpg":"1.3","position":"SG","age":"21","fgPct":".429","teamId":"BRK","stlPerG":"0.3","blkPerG":"0.1"},{"name":"Klay Thompson","ppg":"20.9","apg":"2.5","rpg":"3.9","position":"SG","age":"32","fgPct":".422","teamId":"GSW","stlPerG":"0.6","blkPerG":"0.5"},{"name":"JT Thor","ppg":"2.7","apg":"0.5","rpg":"1.7","position":"PF","age":"20","fgPct":".368","teamId":"CHO","stlPerG":"0.2","blkPerG":"0.2"},{"name":"Matisse Thybulle","ppg":"2.4","apg":"0.5","rpg":"1.2","position":"SG","age":"25","fgPct":".411","teamId":"PHI","stlPerG":"0.8","blkPerG":"0.3"},{"name":"Xavier Tillman Sr.","ppg":"4.5","apg":"0.6","rpg":"2.9","position":"PF","age":"24","fgPct":".586","teamId":"MEM","stlPerG":"0.5","blkPerG":"0.3"},{"name":null,"ppg":null,"apg":null,"rpg":null,"position":null,"age":null,"fgPct":null,"teamId":null,"stlPerG":null,"blkPerG":null},{"name":"Isaiah Todd","ppg":"0.5","apg":"0.0","rpg":"0.0","position":"PF","age":"21","fgPct":".250","teamId":"WAS","stlPerG":"0.0","blkPerG":"0.0"},{"name":"Obi Toppin","ppg":"6.6","apg":"1.0","rpg":"3.5","position":"PF","age":"24","fgPct":".402","teamId":"NYK","stlPerG":"0.4","blkPerG":"0.2"},{"name":"Juan Toscano-Anderson","ppg":"3.0","apg":"0.9","rpg":"2.3","position":"SF","age":"29","fgPct":".534","teamId":"LAL","stlPerG":"0.4","blkPerG":"0.3"},{"name":"Karl-Anthony Towns","ppg":"20.8","apg":"5.3","rpg":"8.2","position":"PF","age":"27","fgPct":".505","teamId":"MIN","stlPerG":"0.8","blkPerG":"0.7"},{"name":"Gary Trent Jr.","ppg":"18.5","apg":"1.5","rpg":"2.4","position":"SG","age":"24","fgPct":".438","teamId":"TOR","stlPerG":"1.7","blkPerG":"0.3"},{"name":"P.J. Tucker","ppg":"3.3","apg":"0.8","rpg":"4.2","position":"PF","age":"37","fgPct":".411","teamId":"PHI","stlPerG":"0.5","blkPerG":"0.3"},{"name":"Myles Turner","ppg":"17.1","apg":"1.4","rpg":"7.8","position":"C","age":"26","fgPct":".558","teamId":"IND","stlPerG":"0.6","blkPerG":"2.4"},{"name":"Jonas Valančiūnas","ppg":"14.8","apg":"1.7","rpg":"9.8","position":"C","age":"30","fgPct":".542","teamId":"NOP","stlPerG":"0.3","blkPerG":"0.5"},{"name":"Jarred Vanderbilt","ppg":"8.6","apg":"2.8","rpg":"8.0","position":"PF","age":"23","fgPct":".566","teamId":"UTA","stlPerG":"1.0","blkPerG":"0.3"},{"name":"Fred VanVleet","ppg":"18.9","apg":"6.4","rpg":"4.3","position":"PG","age":"28","fgPct":".387","teamId":"TOR","stlPerG":"1.5","blkPerG":"0.6"},{"name":"Devin Vassell","ppg":"19.4","apg":"3.6","rpg":"4.0","position":"SG","age":"22","fgPct":".445","teamId":"SAS","stlPerG":"1.2","blkPerG":"0.4"},{"name":"Gabe Vincent","ppg":"9.7","apg":"2.8","rpg":"2.3","position":"PG","age":"26","fgPct":".417","teamId":"MIA","stlPerG":"0.9","blkPerG":"0.1"},{"name":"Noah Vonleh","ppg":"1.1","apg":"0.3","rpg":"2.1","position":"C","age":"27","fgPct":".458","teamId":"BOS","stlPerG":"0.1","blkPerG":"0.3"},{"name":"Nikola Vučević","ppg":"17.5","apg":"3.2","rpg":"11.0","position":"C","age":"32","fgPct":".521","teamId":"CHI","stlPerG":"0.7","blkPerG":"0.9"},{"name":"Dean Wade","ppg":"6.4","apg":"1.0","rpg":"4.1","position":"PF","age":"26","fgPct":".452","teamId":"CLE","stlPerG":"0.7","blkPerG":"0.4"},{"name":"Franz Wagner","ppg":"20.3","apg":"3.3","rpg":"3.9","position":"SF","age":"21","fgPct":".489","teamId":"ORL","stlPerG":"0.9","blkPerG":"0.2"},{"name":"Moritz Wagner","ppg":"11.7","apg":"2.0","rpg":"6.1","position":"C","age":"25","fgPct":".492","teamId":"ORL","stlPerG":"0.8","blkPerG":"0.2"},{"name":"Ish Wainright","ppg":"3.8","apg":"1.0","rpg":"2.1","position":"SF","age":"28","fgPct":".390","teamId":"PHO","stlPerG":"0.7","blkPerG":"0.2"},{"name":"Jabari Walker","ppg":"2.2","apg":"0.6","rpg":"2.3","position":"SF","age":"20","fgPct":".400","teamId":"POR","stlPerG":"0.1","blkPerG":"0.2"},{"name":"Kemba Walker","ppg":"8.0","apg":"2.1","rpg":"1.8","position":"PG","age":"32","fgPct":".421","teamId":"DAL","stlPerG":"0.2","blkPerG":"0.2"},{"name":null,"ppg":null,"apg":null,"rpg":null,"position":null,"age":null,"fgPct":null,"teamId":null,"stlPerG":null,"blkPerG":null},{"name":"Lonnie Walker IV","ppg":"14.7","apg":"1.4","rpg":"2.3","position":"SG","age":"24","fgPct":".455","teamId":"LAL","stlPerG":"0.8","blkPerG":"0.3"},{"name":"John Wall","ppg":"11.4","apg":"5.2","rpg":"2.7","position":"PG","age":"32","fgPct":".408","teamId":"LAC","stlPerG":"0.8","blkPerG":"0.4"},{"name":"T.J. Warren","ppg":"10.5","apg":"1.2","rpg":"3.1","position":"PF","age":"29","fgPct":".521","teamId":"BRK","stlPerG":"0.7","blkPerG":"0.3"},{"name":"Duane Washington Jr.","ppg":"8.0","apg":"2.0","rpg":"1.1","position":"SG","age":"22","fgPct":".369","teamId":"PHO","stlPerG":"0.2","blkPerG":"0.1"},{"name":"P.J. Washington","ppg":"15.2","apg":"2.3","rpg":"4.6","position":"PF","age":"24","fgPct":".443","teamId":"CHO","stlPerG":"0.8","blkPerG":"1.1"},{"name":"TyTy Washington Jr.","ppg":"3.1","apg":"1.3","rpg":"1.2","position":"PG","age":"21","fgPct":".340","teamId":"HOU","stlPerG":"0.4","blkPerG":"0.0"},{"name":"Yuta Watanabe","ppg":"6.7","apg":"0.8","rpg":"2.7","position":"SF","age":"28","fgPct":".531","teamId":"BRK","stlPerG":"0.5","blkPerG":"0.3"},{"name":"Lindy Waters III","ppg":"4.4","apg":"0.8","rpg":"1.7","position":"SG","age":"25","fgPct":".394","teamId":"OKC","stlPerG":"0.3","blkPerG":"0.3"},{"name":"Trendon Watford","ppg":"4.8","apg":"1.5","rpg":"3.5","position":"PF","age":"22","fgPct":".546","teamId":"POR","stlPerG":"0.4","blkPerG":"0.1"},{"name":"Peyton Watson","ppg":"1.0","apg":"0.0","rpg":"0.5","position":"SG","age":"20","fgPct":".333","teamId":"DEN","stlPerG":"0.0","blkPerG":"0.0"},{"name":"Blake Wesley","ppg":"5.8","apg":"1.3","rpg":"1.0","position":"SG","age":"19","fgPct":".643","teamId":"SAS","stlPerG":"0.0","blkPerG":"0.0"},{"name":"Russell Westbrook","ppg":"15.8","apg":"7.7","rpg":"6.6","position":"PG","age":"34","fgPct":".423","teamId":"LAL","stlPerG":"1.0","blkPerG":"0.5"},{"name":"Coby White","ppg":"8.4","apg":"1.8","rpg":"2.6","position":"SG","age":"22","fgPct":".435","teamId":"CHI","stlPerG":"0.8","blkPerG":"0.1"},{"name":"Derrick White","ppg":"9.9","apg":"3.4","rpg":"3.0","position":"SG","age":"28","fgPct":".442","teamId":"BOS","stlPerG":"0.7","blkPerG":"0.9"},{"name":"Jack White","ppg":"0.6","apg":"0.0","rpg":"0.6","position":"SF","age":"25","fgPct":".333","teamId":"DEN","stlPerG":"0.1","blkPerG":"0.2"},{"name":"Joe Wieskamp","ppg":"9.0","apg":"1.0","rpg":"0.0","position":"SF","age":"23","fgPct":".750","teamId":"TOR","stlPerG":"0.0","blkPerG":"0.0"},{"name":"Aaron Wiggins","ppg":"6.4","apg":"1.5","rpg":"3.3","position":"SG","age":"24","fgPct":".491","teamId":"OKC","stlPerG":"0.5","blkPerG":"0.2"},{"name":"Andrew Wiggins","ppg":"18.0","apg":"2.3","rpg":"4.9","position":"SF","age":"27","fgPct":".476","teamId":"GSW","stlPerG":"1.4","blkPerG":"0.9"},{"name":"Alondes Williams","ppg":"0.0","apg":"0.0","rpg":"1.0","position":"SG","age":"23","fgPct":"","teamId":"BRK","stlPerG":"0.0","blkPerG":"0.0"},{"name":"Grant Williams","ppg":"8.8","apg":"1.8","rpg":"4.7","position":"PF","age":"24","fgPct":".486","teamId":"BOS","stlPerG":"0.7","blkPerG":"0.4"},{"name":null,"ppg":null,"apg":null,"rpg":null,"position":null,"age":null,"fgPct":null,"teamId":null,"stlPerG":null,"blkPerG":null},{"name":"Jalen Williams","ppg":"11.7","apg":"2.9","rpg":"3.9","position":"SG","age":"21","fgPct":".507","teamId":"OKC","stlPerG":"1.0","blkPerG":"0.5"},{"name":"Jaylin Williams","ppg":"3.9","apg":"1.1","rpg":"3.6","position":"PF","age":"20","fgPct":".431","teamId":"OKC","stlPerG":"0.4","blkPerG":"0.1"},{"name":"Kenrich Williams","ppg":"7.6","apg":"1.7","rpg":"4.8","position":"PF","age":"28","fgPct":".544","teamId":"OKC","stlPerG":"0.7","blkPerG":"0.3"},{"name":"Mark Williams","ppg":"6.7","apg":"0.3","rpg":"5.7","position":"C","age":"21","fgPct":".600","teamId":"CHO","stlPerG":"0.5","blkPerG":"0.9"},{"name":"Patrick Williams","ppg":"10.0","apg":"1.3","rpg":"4.1","position":"PF","age":"21","fgPct":".460","teamId":"CHI","stlPerG":"0.7","blkPerG":"0.9"},{"name":"Robert Williams","ppg":"8.1","apg":"1.6","rpg":"8.1","position":"C","age":"25","fgPct":".761","teamId":"BOS","stlPerG":"0.5","blkPerG":"1.2"},{"name":"Vince Williams Jr.","ppg":"0.9","apg":"0.4","rpg":"0.6","position":"SG","age":"22","fgPct":".273","teamId":"MEM","stlPerG":"0.5","blkPerG":"0.1"},{"name":"Ziaire Williams","ppg":"6.4","apg":"1.0","rpg":"2.8","position":"SF","age":"21","fgPct":".438","teamId":"MEM","stlPerG":"0.4","blkPerG":"0.2"},{"name":"Zion Williamson","ppg":"26.0","apg":"4.6","rpg":"7.0","position":"PF","age":"22","fgPct":".608","teamId":"NOP","stlPerG":"1.1","blkPerG":"0.6"},{"name":"Justise Winslow","ppg":"6.8","apg":"3.4","rpg":"5.0","position":"SF","age":"26","fgPct":".409","teamId":"POR","stlPerG":"1.0","blkPerG":"0.4"},{"name":"James Wiseman","ppg":"6.8","apg":"0.7","rpg":"3.6","position":"C","age":"21","fgPct":".609","teamId":"GSW","stlPerG":"0.1","blkPerG":"0.4"},{"name":"Christian Wood","ppg":"18.4","apg":"1.7","rpg":"8.4","position":"C","age":"27","fgPct":".535","teamId":"DAL","stlPerG":"0.5","blkPerG":"1.3"},{"name":"Delon Wright","ppg":"5.9","apg":"3.4","rpg":"2.7","position":"PG","age":"30","fgPct":".402","teamId":"WAS","stlPerG":"2.1","blkPerG":"0.4"},{"name":"McKinley Wright IV","ppg":"1.9","apg":"1.4","rpg":"1.1","position":"PG","age":"24","fgPct":".417","teamId":"DAL","stlPerG":"0.5","blkPerG":"0.2"},{"name":"Thaddeus Young","ppg":"4.8","apg":"1.6","rpg":"3.6","position":"PF","age":"34","fgPct":".549","teamId":"TOR","stlPerG":"1.0","blkPerG":"0.1"},{"name":"Trae Young","ppg":"27.2","apg":"9.8","rpg":"2.9","position":"PG","age":"24","fgPct":".424","teamId":"ATL","stlPerG":"1.0","blkPerG":"0.2"},{"name":"Ivica Zubac","ppg":"10.3","apg":"1.0","rpg":"10.3","position":"C","age":"25","fgPct":".619","teamId":"LAC","stlPerG":"0.4","blkPerG":"1.3"}]